{
  "granularity": "hourly",
  "data": [
    {
      "ts": "2026-02-11T01:00:00",
      "raw": -0.20277333496646446,
      "smoothed": -0.20277333496646446,
      "n_posts": 2,
      "n_positive": 1,
      "n_negative": 1,
      "directional_bias": 0.0
    },
    {
      "ts": "2026-02-11T10:00:00",
      "raw": -0.5684850998222828,
      "smoothed": -0.27591568793762816,
      "n_posts": 1,
      "n_positive": 0,
      "n_negative": 1,
      "directional_bias": -1.0
    },
    {
      "ts": "2026-02-11T14:00:00",
      "raw": -0.2013232596218586,
      "smoothed": -0.26099720227447426,
      "n_posts": 1,
      "n_positive": 0,
      "n_negative": 1,
      "directional_bias": -1.0
    },
    {
      "ts": "2026-02-11T18:00:00",
      "raw": -0.8594758827239274,
      "smoothed": -0.3806929383643649,
      "n_posts": 1,
      "n_positive": 0,
      "n_negative": 1,
      "directional_bias": -1.0
    },
    {
      "ts": "2026-02-11T21:00:00",
      "raw": -0.8343053944408895,
      "smoothed": -0.47141542957966986,
      "n_posts": 1,
      "n_positive": 0,
      "n_negative": 1,
      "directional_bias": -1.0
    },
    {
      "ts": "2026-02-12T05:00:00",
      "raw": 0.06641950272023678,
      "smoothed": 0.06641950272023678,
      "n_posts": 1,
      "n_positive": 1,
      "n_negative": 0,
      "directional_bias": 1.0
    },
    {
      "ts": "2026-02-12T10:00:00",
      "raw": 0.06911169365048409,
      "smoothed": 0.06695794090628625,
      "n_posts": 1,
      "n_positive": 1,
      "n_negative": 0,
      "directional_bias": 1.0
    },
    {
      "ts": "2026-02-12T15:00:00",
      "raw": 0.049269819632172585,
      "smoothed": 0.06342031665146351,
      "n_posts": 1,
      "n_positive": 1,
      "n_negative": 0,
      "directional_bias": 1.0
    },
    {
      "ts": "2026-02-12T18:00:00",
      "raw": -0.8318168446421623,
      "smoothed": -0.11562711560726166,
      "n_posts": 1,
      "n_positive": 0,
      "n_negative": 1,
      "directional_bias": -1.0
    },
    {
      "ts": "2026-02-13T00:00:00",
      "raw": 0.11532673612236977,
      "smoothed": 0.11532673612236977,
      "n_posts": 1,
      "n_positive": 1,
      "n_negative": 0,
      "directional_bias": 1.0
    },
    {
      "ts": "2026-02-13T04:00:00",
      "raw": -0.06058044731616974,
      "smoothed": 0.08014529943466187,
      "n_posts": 1,
      "n_positive": 0,
      "n_negative": 1,
      "directional_bias": -1.0
    },
    {
      "ts": "2026-02-13T05:00:00",
      "raw": 0.037682972848415375,
      "smoothed": 0.07165283411741256,
      "n_posts": 1,
      "n_positive": 1,
      "n_negative": 0,
      "directional_bias": 1.0
    },
    {
      "ts": "2026-02-13T10:00:00",
      "raw": -0.021691016852855682,
      "smoothed": 0.05298406392335892,
      "n_posts": 1,
      "n_positive": 0,
      "n_negative": 1,
      "directional_bias": -1.0
    },
    {
      "ts": "2026-02-13T16:00:00",
      "raw": 0.021879953797906637,
      "smoothed": 0.046763241898268464,
      "n_posts": 2,
      "n_positive": 1,
      "n_negative": 1,
      "directional_bias": 0.0
    },
    {
      "ts": "2026-02-13T18:00:00",
      "raw": 0.016622697934508324,
      "smoothed": 0.04073513310551644,
      "n_posts": 1,
      "n_positive": 1,
      "n_negative": 0,
      "directional_bias": 1.0
    },
    {
      "ts": "2026-02-13T19:00:00",
      "raw": -0.7617699801921844,
      "smoothed": -0.11976588955402376,
      "n_posts": 1,
      "n_positive": 0,
      "n_negative": 1,
      "directional_bias": -1.0
    },
    {
      "ts": "2026-02-13T20:00:00",
      "raw": 0.8873439878225325,
      "smoothed": 0.0816560859212875,
      "n_posts": 1,
      "n_positive": 1,
      "n_negative": 0,
      "directional_bias": 1.0
    },
    {
      "ts": "2026-02-14T12:00:00",
      "raw": 0.45136338472366333,
      "smoothed": 0.45136338472366333,
      "n_posts": 1,
      "n_positive": 1,
      "n_negative": 0,
      "directional_bias": 1.0
    },
    {
      "ts": "2026-02-14T13:00:00",
      "raw": 0.03932868968695402,
      "smoothed": 0.3689564457163215,
      "n_posts": 2,
      "n_positive": 2,
      "n_negative": 0,
      "directional_bias": 1.0
    },
    {
      "ts": "2026-02-14T16:00:00",
      "raw": -0.8924691453576088,
      "smoothed": 0.11667132750153547,
      "n_posts": 1,
      "n_positive": 0,
      "n_negative": 1,
      "directional_bias": -1.0
    },
    {
      "ts": "2026-02-14T20:00:00",
      "raw": 0.03936717472970486,
      "smoothed": 0.10121049694716935,
      "n_posts": 1,
      "n_positive": 1,
      "n_negative": 0,
      "directional_bias": 1.0
    },
    {
      "ts": "2026-02-15T02:00:00",
      "raw": -0.0034709386527538295,
      "smoothed": -0.0034709386527538295,
      "n_posts": 1,
      "n_positive": 0,
      "n_negative": 1,
      "directional_bias": -1.0
    },
    {
      "ts": "2026-02-15T05:00:00",
      "raw": -0.2893430106341839,
      "smoothed": -0.06064535304903985,
      "n_posts": 2,
      "n_positive": 1,
      "n_negative": 1,
      "directional_bias": 0.0
    },
    {
      "ts": "2026-02-15T09:00:00",
      "raw": 0.019221927970647812,
      "smoothed": -0.04467189684510232,
      "n_posts": 1,
      "n_positive": 1,
      "n_negative": 0,
      "directional_bias": 1.0
    },
    {
      "ts": "2026-02-15T11:00:00",
      "raw": 0.03060462325811386,
      "smoothed": -0.029616592824459085,
      "n_posts": 1,
      "n_positive": 1,
      "n_negative": 0,
      "directional_bias": 1.0
    },
    {
      "ts": "2026-02-15T14:00:00",
      "raw": -0.7398831602185965,
      "smoothed": -0.17166990630328657,
      "n_posts": 2,
      "n_positive": 0,
      "n_negative": 2,
      "directional_bias": -1.0
    },
    {
      "ts": "2026-02-15T18:00:00",
      "raw": 0.015224777162075043,
      "smoothed": -0.13429096961021425,
      "n_posts": 1,
      "n_positive": 1,
      "n_negative": 0,
      "directional_bias": 1.0
    },
    {
      "ts": "2026-02-16T00:00:00",
      "raw": -0.210768461227417,
      "smoothed": -0.210768461227417,
      "n_posts": 1,
      "n_positive": 0,
      "n_negative": 1,
      "directional_bias": -1.0
    },
    {
      "ts": "2026-02-16T04:00:00",
      "raw": -0.5248666703701019,
      "smoothed": -0.273588103055954,
      "n_posts": 1,
      "n_positive": 0,
      "n_negative": 1,
      "directional_bias": -1.0
    },
    {
      "ts": "2026-02-16T06:00:00",
      "raw": -0.5906023941934109,
      "smoothed": -0.3369909612834454,
      "n_posts": 1,
      "n_positive": 0,
      "n_negative": 1,
      "directional_bias": -1.0
    },
    {
      "ts": "2026-02-16T09:00:00",
      "raw": -0.27157040052115916,
      "smoothed": -0.32390684913098816,
      "n_posts": 5,
      "n_positive": 2,
      "n_negative": 3,
      "directional_bias": -0.2
    },
    {
      "ts": "2026-02-16T10:00:00",
      "raw": -0.029726520180702213,
      "smoothed": -0.265070783340931,
      "n_posts": 1,
      "n_positive": 0,
      "n_negative": 1,
      "directional_bias": -1.0
    },
    {
      "ts": "2026-02-16T11:00:00",
      "raw": 0.043434759601950645,
      "smoothed": -0.20336967475235468,
      "n_posts": 1,
      "n_positive": 1,
      "n_negative": 0,
      "directional_bias": 1.0
    },
    {
      "ts": "2026-02-16T12:00:00",
      "raw": -0.7997199908519785,
      "smoothed": -0.3226397379722795,
      "n_posts": 3,
      "n_positive": 0,
      "n_negative": 3,
      "directional_bias": -1.0
    },
    {
      "ts": "2026-02-16T13:00:00",
      "raw": -0.3267228923299733,
      "smoothed": -0.3234563688438183,
      "n_posts": 3,
      "n_positive": 1,
      "n_negative": 2,
      "directional_bias": -0.3333333333333333
    },
    {
      "ts": "2026-02-16T14:00:00",
      "raw": -0.5173009386943543,
      "smoothed": -0.3622252828139255,
      "n_posts": 3,
      "n_positive": 1,
      "n_negative": 2,
      "directional_bias": -0.3333333333333333
    },
    {
      "ts": "2026-02-16T15:00:00",
      "raw": -0.09958345536142588,
      "smoothed": -0.3096969173234256,
      "n_posts": 2,
      "n_positive": 1,
      "n_negative": 1,
      "directional_bias": 0.0
    },
    {
      "ts": "2026-02-16T16:00:00",
      "raw": 0.32345591158546666,
      "smoothed": -0.18306635154164713,
      "n_posts": 8,
      "n_positive": 8,
      "n_negative": 0,
      "directional_bias": 1.0
    },
    {
      "ts": "2026-02-16T17:00:00",
      "raw": -0.4733210230867068,
      "smoothed": -0.24111728585065909,
      "n_posts": 9,
      "n_positive": 3,
      "n_negative": 6,
      "directional_bias": -0.3333333333333333
    },
    {
      "ts": "2026-02-16T18:00:00",
      "raw": -0.3911681554745883,
      "smoothed": -0.27112745977544495,
      "n_posts": 6,
      "n_positive": 1,
      "n_negative": 5,
      "directional_bias": -0.6666666666666666
    },
    {
      "ts": "2026-02-16T19:00:00",
      "raw": -0.18173794839531177,
      "smoothed": -0.25324955749941835,
      "n_posts": 5,
      "n_positive": 2,
      "n_negative": 3,
      "directional_bias": -0.2
    },
    {
      "ts": "2026-02-16T20:00:00",
      "raw": -0.9327400964684784,
      "smoothed": -0.3891476652932304,
      "n_posts": 2,
      "n_positive": 0,
      "n_negative": 2,
      "directional_bias": -1.0
    },
    {
      "ts": "2026-02-16T21:00:00",
      "raw": 0.0033512040972709656,
      "smoothed": -0.31064789141513016,
      "n_posts": 1,
      "n_positive": 1,
      "n_negative": 0,
      "directional_bias": 1.0
    },
    {
      "ts": "2026-02-16T22:00:00",
      "raw": 0.11942632485400226,
      "smoothed": -0.2246330481613037,
      "n_posts": 3,
      "n_positive": 3,
      "n_negative": 0,
      "directional_bias": 1.0
    },
    {
      "ts": "2026-02-16T23:00:00",
      "raw": 0.06236183039016193,
      "smoothed": -0.16723407245101057,
      "n_posts": 8,
      "n_positive": 5,
      "n_negative": 3,
      "directional_bias": 0.25
    },
    {
      "ts": "2026-02-17T03:00:00",
      "raw": -0.41917192935943604,
      "smoothed": -0.41917192935943604,
      "n_posts": 2,
      "n_positive": 1,
      "n_negative": 1,
      "directional_bias": 0.0
    },
    {
      "ts": "2026-02-17T04:00:00",
      "raw": -0.2701578058768064,
      "smoothed": -0.38936910466291014,
      "n_posts": 4,
      "n_positive": 2,
      "n_negative": 2,
      "directional_bias": 0.0
    },
    {
      "ts": "2026-02-17T05:00:00",
      "raw": -0.1333563367313728,
      "smoothed": -0.3381665510766027,
      "n_posts": 7,
      "n_positive": 4,
      "n_negative": 3,
      "directional_bias": 0.14285714285714285
    },
    {
      "ts": "2026-02-17T06:00:00",
      "raw": 0.4931518014520407,
      "smoothed": -0.17190288057087402,
      "n_posts": 5,
      "n_positive": 3,
      "n_negative": 2,
      "directional_bias": 0.2
    },
    {
      "ts": "2026-02-17T07:00:00",
      "raw": -0.07253920547664165,
      "smoothed": -0.15203014555202754,
      "n_posts": 5,
      "n_positive": 2,
      "n_negative": 3,
      "directional_bias": -0.2
    },
    {
      "ts": "2026-02-17T08:00:00",
      "raw": -0.30072760154657496,
      "smoothed": -0.18176963675093705,
      "n_posts": 3,
      "n_positive": 1,
      "n_negative": 2,
      "directional_bias": -0.3333333333333333
    },
    {
      "ts": "2026-02-17T09:00:00",
      "raw": 0.1645051866488637,
      "smoothed": -0.11251467207097689,
      "n_posts": 9,
      "n_positive": 6,
      "n_negative": 3,
      "directional_bias": 0.3333333333333333
    },
    {
      "ts": "2026-02-17T10:00:00",
      "raw": -0.2265713030064945,
      "smoothed": -0.13532599825808042,
      "n_posts": 11,
      "n_positive": 4,
      "n_negative": 7,
      "directional_bias": -0.2727272727272727
    },
    {
      "ts": "2026-02-17T11:00:00",
      "raw": 0.3623232194061937,
      "smoothed": -0.0357961547252256,
      "n_posts": 5,
      "n_positive": 3,
      "n_negative": 2,
      "directional_bias": 0.2
    }
  ]
}