{
  "granularity": "hourly",
  "data": [
    {
      "ts": "2026-03-02T19:00:00",
      "raw": -0.004559529945254326,
      "smoothed": -0.004559529945254326,
      "n_posts": 1,
      "n_positive": 0,
      "n_negative": 1,
      "directional_bias": -1.0
    },
    {
      "ts": "2026-03-03T11:00:00",
      "raw": -0.7205210030078888,
      "smoothed": -0.7205210030078888,
      "n_posts": 1,
      "n_positive": 0,
      "n_negative": 1,
      "directional_bias": -1.0
    },
    {
      "ts": "2026-03-03T22:00:00",
      "raw": -0.8648250270634888,
      "smoothed": -0.7493818078190089,
      "n_posts": 1,
      "n_positive": 0,
      "n_negative": 1,
      "directional_bias": -1.0
    },
    {
      "ts": "2026-03-04T19:00:00",
      "raw": 0.4319647438824177,
      "smoothed": 0.4319647438824177,
      "n_posts": 1,
      "n_positive": 1,
      "n_negative": 0,
      "directional_bias": 1.0
    },
    {
      "ts": "2026-03-04T20:00:00",
      "raw": 0.8541413974016906,
      "smoothed": 0.5164000745862722,
      "n_posts": 2,
      "n_positive": 2,
      "n_negative": 0,
      "directional_bias": 1.0
    },
    {
      "ts": "2026-03-04T21:00:00",
      "raw": 0.6926593743264675,
      "smoothed": 0.5516519345343114,
      "n_posts": 1,
      "n_positive": 1,
      "n_negative": 0,
      "directional_bias": 1.0
    },
    {
      "ts": "2026-03-05T04:00:00",
      "raw": -0.8745901249349117,
      "smoothed": -0.8745901249349117,
      "n_posts": 1,
      "n_positive": 0,
      "n_negative": 1,
      "directional_bias": -1.0
    },
    {
      "ts": "2026-03-05T15:00:00",
      "raw": 0.24932459617654484,
      "smoothed": -0.6498071807126204,
      "n_posts": 3,
      "n_positive": 2,
      "n_negative": 1,
      "directional_bias": 0.3333333333333333
    },
    {
      "ts": "2026-03-05T19:00:00",
      "raw": -0.599135858938098,
      "smoothed": -0.639672916357716,
      "n_posts": 1,
      "n_positive": 0,
      "n_negative": 1,
      "directional_bias": -1.0
    },
    {
      "ts": "2026-03-05T20:00:00",
      "raw": 0.03720247372984886,
      "smoothed": -0.504297838340203,
      "n_posts": 1,
      "n_positive": 1,
      "n_negative": 0,
      "directional_bias": 1.0
    },
    {
      "ts": "2026-03-05T21:00:00",
      "raw": -0.1791726325949033,
      "smoothed": -0.4392727971911431,
      "n_posts": 3,
      "n_positive": 2,
      "n_negative": 1,
      "directional_bias": 0.3333333333333333
    },
    {
      "ts": "2026-03-05T22:00:00",
      "raw": -0.005332935601472855,
      "smoothed": -0.35248482487320904,
      "n_posts": 1,
      "n_positive": 0,
      "n_negative": 1,
      "directional_bias": -1.0
    },
    {
      "ts": "2026-03-06T03:00:00",
      "raw": -0.7878317106515169,
      "smoothed": -0.7878317106515169,
      "n_posts": 1,
      "n_positive": 0,
      "n_negative": 1,
      "directional_bias": -1.0
    },
    {
      "ts": "2026-03-06T07:00:00",
      "raw": -0.9461460905149579,
      "smoothed": -0.8194945866242052,
      "n_posts": 1,
      "n_positive": 0,
      "n_negative": 1,
      "directional_bias": -1.0
    },
    {
      "ts": "2026-03-06T10:00:00",
      "raw": 0.0253919530659914,
      "smoothed": -0.6505172786861659,
      "n_posts": 1,
      "n_positive": 1,
      "n_negative": 0,
      "directional_bias": 1.0
    },
    {
      "ts": "2026-03-06T12:00:00",
      "raw": -0.39360265247523785,
      "smoothed": -0.5991343534439804,
      "n_posts": 2,
      "n_positive": 1,
      "n_negative": 1,
      "directional_bias": 0.0
    },
    {
      "ts": "2026-03-06T13:00:00",
      "raw": 0.0052504148334264755,
      "smoothed": -0.478257399788499,
      "n_posts": 1,
      "n_positive": 1,
      "n_negative": 0,
      "directional_bias": 1.0
    },
    {
      "ts": "2026-03-06T14:00:00",
      "raw": -0.44996549515053635,
      "smoothed": -0.4725990188609065,
      "n_posts": 2,
      "n_positive": 1,
      "n_negative": 1,
      "directional_bias": 0.0
    },
    {
      "ts": "2026-03-06T15:00:00",
      "raw": -0.06489920616149901,
      "smoothed": -0.391059056321025,
      "n_posts": 2,
      "n_positive": 1,
      "n_negative": 1,
      "directional_bias": 0.0
    },
    {
      "ts": "2026-03-06T16:00:00",
      "raw": 0.018217090517282486,
      "smoothed": -0.30920382695336357,
      "n_posts": 1,
      "n_positive": 1,
      "n_negative": 0,
      "directional_bias": 1.0
    },
    {
      "ts": "2026-03-06T20:00:00",
      "raw": -0.23432409390807152,
      "smoothed": -0.29422788034430514,
      "n_posts": 2,
      "n_positive": 0,
      "n_negative": 2,
      "directional_bias": -1.0
    },
    {
      "ts": "2026-03-06T21:00:00",
      "raw": 0.46928817084567104,
      "smoothed": -0.14152467010630992,
      "n_posts": 2,
      "n_positive": 2,
      "n_negative": 0,
      "directional_bias": 1.0
    },
    {
      "ts": "2026-03-06T22:00:00",
      "raw": -0.8502173162996768,
      "smoothed": -0.2832631993449833,
      "n_posts": 1,
      "n_positive": 0,
      "n_negative": 1,
      "directional_bias": -1.0
    },
    {
      "ts": "2026-03-06T23:00:00",
      "raw": 0.5227003991603851,
      "smoothed": -0.1220704796439096,
      "n_posts": 1,
      "n_positive": 1,
      "n_negative": 0,
      "directional_bias": 1.0
    },
    {
      "ts": "2026-03-07T05:00:00",
      "raw": -0.3001299165189267,
      "smoothed": -0.3001299165189267,
      "n_posts": 3,
      "n_positive": 0,
      "n_negative": 3,
      "directional_bias": -1.0
    },
    {
      "ts": "2026-03-07T06:00:00",
      "raw": -0.4718736335635185,
      "smoothed": -0.33447865992784503,
      "n_posts": 3,
      "n_positive": 1,
      "n_negative": 2,
      "directional_bias": -0.3333333333333333
    },
    {
      "ts": "2026-03-07T12:00:00",
      "raw": -0.023178845643997192,
      "smoothed": -0.2722186970710755,
      "n_posts": 1,
      "n_positive": 0,
      "n_negative": 1,
      "directional_bias": -1.0
    },
    {
      "ts": "2026-03-07T14:00:00",
      "raw": 0.008417729288339615,
      "smoothed": -0.21609141179919247,
      "n_posts": 1,
      "n_positive": 1,
      "n_negative": 0,
      "directional_bias": 1.0
    },
    {
      "ts": "2026-03-07T15:00:00",
      "raw": -0.14175690633469615,
      "smoothed": -0.2012245107062932,
      "n_posts": 5,
      "n_positive": 3,
      "n_negative": 2,
      "directional_bias": 0.2
    },
    {
      "ts": "2026-03-07T16:00:00",
      "raw": -0.05903660743073983,
      "smoothed": -0.17278693005118254,
      "n_posts": 2,
      "n_positive": 0,
      "n_negative": 2,
      "directional_bias": -1.0
    },
    {
      "ts": "2026-03-07T17:00:00",
      "raw": 0.09605822975144666,
      "smoothed": -0.1190178980906567,
      "n_posts": 3,
      "n_positive": 2,
      "n_negative": 1,
      "directional_bias": 0.3333333333333333
    },
    {
      "ts": "2026-03-07T18:00:00",
      "raw": -0.12081160582602024,
      "smoothed": -0.11937663963772942,
      "n_posts": 1,
      "n_positive": 0,
      "n_negative": 1,
      "directional_bias": -1.0
    },
    {
      "ts": "2026-03-07T19:00:00",
      "raw": -0.5164071191102266,
      "smoothed": -0.19878273553222886,
      "n_posts": 1,
      "n_positive": 0,
      "n_negative": 1,
      "directional_bias": -1.0
    },
    {
      "ts": "2026-03-07T20:00:00",
      "raw": 0.11997192539274691,
      "smoothed": -0.1350318033472337,
      "n_posts": 1,
      "n_positive": 1,
      "n_negative": 0,
      "directional_bias": 1.0
    },
    {
      "ts": "2026-03-07T21:00:00",
      "raw": -0.1077682301402092,
      "smoothed": -0.1295790887058288,
      "n_posts": 1,
      "n_positive": 0,
      "n_negative": 1,
      "directional_bias": -1.0
    },
    {
      "ts": "2026-03-07T22:00:00",
      "raw": 0.028162476606667042,
      "smoothed": -0.09803077564332964,
      "n_posts": 1,
      "n_positive": 1,
      "n_negative": 0,
      "directional_bias": 1.0
    },
    {
      "ts": "2026-03-07T23:00:00",
      "raw": 0.05054035037755966,
      "smoothed": -0.06831655043915177,
      "n_posts": 1,
      "n_positive": 1,
      "n_negative": 0,
      "directional_bias": 1.0
    },
    {
      "ts": "2026-03-08T00:00:00",
      "raw": -0.01334371417760849,
      "smoothed": -0.01334371417760849,
      "n_posts": 1,
      "n_positive": 0,
      "n_negative": 1,
      "directional_bias": -1.0
    },
    {
      "ts": "2026-03-08T02:00:00",
      "raw": 0.08983281021937728,
      "smoothed": 0.007291590701788664,
      "n_posts": 2,
      "n_positive": 1,
      "n_negative": 1,
      "directional_bias": 0.0
    },
    {
      "ts": "2026-03-08T03:00:00",
      "raw": -0.08290795981884003,
      "smoothed": -0.010748319402337074,
      "n_posts": 2,
      "n_positive": 1,
      "n_negative": 1,
      "directional_bias": 0.0
    },
    {
      "ts": "2026-03-08T04:00:00",
      "raw": -0.44401625450700516,
      "smoothed": -0.09740190642327069,
      "n_posts": 2,
      "n_positive": 1,
      "n_negative": 1,
      "directional_bias": 0.0
    },
    {
      "ts": "2026-03-08T05:00:00",
      "raw": -0.2183225378394127,
      "smoothed": -0.12158603270649909,
      "n_posts": 2,
      "n_positive": 0,
      "n_negative": 2,
      "directional_bias": -1.0
    },
    {
      "ts": "2026-03-08T07:00:00",
      "raw": -0.6234633069146763,
      "smoothed": -0.22196148754813455,
      "n_posts": 2,
      "n_positive": 0,
      "n_negative": 2,
      "directional_bias": -1.0
    },
    {
      "ts": "2026-03-08T08:00:00",
      "raw": 0.02221052162349224,
      "smoothed": -0.17312708571380922,
      "n_posts": 1,
      "n_positive": 1,
      "n_negative": 0,
      "directional_bias": 1.0
    },
    {
      "ts": "2026-03-08T09:00:00",
      "raw": 0.15299454128200357,
      "smoothed": -0.10790276031464666,
      "n_posts": 2,
      "n_positive": 2,
      "n_negative": 0,
      "directional_bias": 1.0
    },
    {
      "ts": "2026-03-08T10:00:00",
      "raw": 0.12680114433169365,
      "smoothed": -0.06096197938537859,
      "n_posts": 4,
      "n_positive": 3,
      "n_negative": 1,
      "directional_bias": 0.5
    },
    {
      "ts": "2026-03-08T11:00:00",
      "raw": -0.1904356885701418,
      "smoothed": -0.08685672122233123,
      "n_posts": 5,
      "n_positive": 3,
      "n_negative": 2,
      "directional_bias": 0.2
    },
    {
      "ts": "2026-03-08T12:00:00",
      "raw": 0.0004296097904443741,
      "smoothed": -0.06939945501977611,
      "n_posts": 1,
      "n_positive": 1,
      "n_negative": 0,
      "directional_bias": 1.0
    },
    {
      "ts": "2026-03-08T13:00:00",
      "raw": -0.08060435152479582,
      "smoothed": -0.07164043432078006,
      "n_posts": 7,
      "n_positive": 3,
      "n_negative": 4,
      "directional_bias": -0.14285714285714285
    },
    {
      "ts": "2026-03-08T14:00:00",
      "raw": -0.16551701258867982,
      "smoothed": -0.09041574997436001,
      "n_posts": 4,
      "n_positive": 1,
      "n_negative": 3,
      "directional_bias": -0.5
    },
    {
      "ts": "2026-03-08T15:00:00",
      "raw": 0.13306913897395134,
      "smoothed": -0.04571877218469775,
      "n_posts": 3,
      "n_positive": 3,
      "n_negative": 0,
      "directional_bias": 1.0
    },
    {
      "ts": "2026-03-08T16:00:00",
      "raw": 0.17637559656492047,
      "smoothed": -0.0012998984347740994,
      "n_posts": 3,
      "n_positive": 2,
      "n_negative": 1,
      "directional_bias": 0.3333333333333333
    },
    {
      "ts": "2026-03-08T17:00:00",
      "raw": 0.21078175647805136,
      "smoothed": 0.041116432547790994,
      "n_posts": 3,
      "n_positive": 2,
      "n_negative": 1,
      "directional_bias": 0.3333333333333333
    },
    {
      "ts": "2026-03-08T18:00:00",
      "raw": -0.1674428022932261,
      "smoothed": -0.0005954144204124295,
      "n_posts": 7,
      "n_positive": 2,
      "n_negative": 5,
      "directional_bias": -0.42857142857142855
    },
    {
      "ts": "2026-03-08T19:00:00",
      "raw": -0.23940819942138408,
      "smoothed": -0.048357971420606764,
      "n_posts": 2,
      "n_positive": 1,
      "n_negative": 1,
      "directional_bias": 0.0
    },
    {
      "ts": "2026-03-08T20:00:00",
      "raw": 0.1746253698416378,
      "smoothed": -0.0037613031681578563,
      "n_posts": 4,
      "n_positive": 2,
      "n_negative": 2,
      "directional_bias": 0.0
    },
    {
      "ts": "2026-03-08T21:00:00",
      "raw": 0.2485128898064003,
      "smoothed": 0.04669353542675377,
      "n_posts": 3,
      "n_positive": 3,
      "n_negative": 0,
      "directional_bias": 1.0
    },
    {
      "ts": "2026-03-08T22:00:00",
      "raw": -0.1565466441044753,
      "smoothed": 0.006045499520507952,
      "n_posts": 4,
      "n_positive": 3,
      "n_negative": 1,
      "directional_bias": 0.5
    },
    {
      "ts": "2026-03-08T23:00:00",
      "raw": -0.17977709174156187,
      "smoothed": -0.031119018731906013,
      "n_posts": 5,
      "n_positive": 3,
      "n_negative": 2,
      "directional_bias": 0.2
    },
    {
      "ts": "2026-03-09T00:00:00",
      "raw": 0.12935444774727026,
      "smoothed": 0.12935444774727026,
      "n_posts": 6,
      "n_positive": 5,
      "n_negative": 1,
      "directional_bias": 0.6666666666666666
    },
    {
      "ts": "2026-03-09T01:00:00",
      "raw": 0.03889363259077072,
      "smoothed": 0.11126228471597036,
      "n_posts": 1,
      "n_positive": 1,
      "n_negative": 0,
      "directional_bias": 1.0
    },
    {
      "ts": "2026-03-09T02:00:00",
      "raw": -0.29653645524134237,
      "smoothed": 0.02970253672450781,
      "n_posts": 9,
      "n_positive": 6,
      "n_negative": 3,
      "directional_bias": 0.3333333333333333
    },
    {
      "ts": "2026-03-09T03:00:00",
      "raw": 0.12672406882047654,
      "smoothed": 0.04910684314370156,
      "n_posts": 5,
      "n_positive": 3,
      "n_negative": 2,
      "directional_bias": 0.2
    }
  ]
}