{
  "granularity": "hourly",
  "data": [
    {
      "ts": "2026-03-01T10:00:00",
      "raw": 0.04284433275461197,
      "smoothed": 0.04284433275461197,
      "n_posts": 1,
      "n_positive": 1,
      "n_negative": 0,
      "directional_bias": 1.0
    },
    {
      "ts": "2026-03-02T17:00:00",
      "raw": -0.3107903003692627,
      "smoothed": -0.3107903003692627,
      "n_posts": 1,
      "n_positive": 0,
      "n_negative": 1,
      "directional_bias": -1.0
    },
    {
      "ts": "2026-03-02T19:00:00",
      "raw": -0.004559529945254326,
      "smoothed": -0.24954414628446103,
      "n_posts": 1,
      "n_positive": 0,
      "n_negative": 1,
      "directional_bias": -1.0
    },
    {
      "ts": "2026-03-02T20:00:00",
      "raw": -0.2664238214492798,
      "smoothed": -0.2529200813174248,
      "n_posts": 1,
      "n_positive": 0,
      "n_negative": 1,
      "directional_bias": -1.0
    },
    {
      "ts": "2026-03-03T16:00:00",
      "raw": 0.006563816219568252,
      "smoothed": 0.006563816219568252,
      "n_posts": 1,
      "n_positive": 1,
      "n_negative": 0,
      "directional_bias": 1.0
    },
    {
      "ts": "2026-03-03T22:00:00",
      "raw": -0.8834368754178287,
      "smoothed": -0.17143632210791115,
      "n_posts": 2,
      "n_positive": 0,
      "n_negative": 2,
      "directional_bias": -1.0
    },
    {
      "ts": "2026-03-04T14:00:00",
      "raw": -0.01716713421046734,
      "smoothed": -0.01716713421046734,
      "n_posts": 1,
      "n_positive": 0,
      "n_negative": 1,
      "directional_bias": -1.0
    },
    {
      "ts": "2026-03-04T16:00:00",
      "raw": 0.14410986378788948,
      "smoothed": 0.015088265389204027,
      "n_posts": 1,
      "n_positive": 1,
      "n_negative": 0,
      "directional_bias": 1.0
    },
    {
      "ts": "2026-03-04T17:00:00",
      "raw": 0.6461584120988846,
      "smoothed": 0.14130229473114014,
      "n_posts": 1,
      "n_positive": 1,
      "n_negative": 0,
      "directional_bias": 1.0
    },
    {
      "ts": "2026-03-04T18:00:00",
      "raw": 0.5749376565217972,
      "smoothed": 0.22802936708927157,
      "n_posts": 1,
      "n_positive": 1,
      "n_negative": 0,
      "directional_bias": 1.0
    },
    {
      "ts": "2026-03-04T19:00:00",
      "raw": 0.4319647438824177,
      "smoothed": 0.2688164424479008,
      "n_posts": 1,
      "n_positive": 1,
      "n_negative": 0,
      "directional_bias": 1.0
    },
    {
      "ts": "2026-03-04T20:00:00",
      "raw": 0.657480715463559,
      "smoothed": 0.3465492970510325,
      "n_posts": 3,
      "n_positive": 3,
      "n_negative": 0,
      "directional_bias": 1.0
    },
    {
      "ts": "2026-03-04T21:00:00",
      "raw": 0.03637397661805153,
      "smoothed": 0.2845142329644363,
      "n_posts": 2,
      "n_positive": 1,
      "n_negative": 1,
      "directional_bias": 0.0
    },
    {
      "ts": "2026-03-05T01:00:00",
      "raw": 0.25130842439830303,
      "smoothed": 0.25130842439830303,
      "n_posts": 2,
      "n_positive": 1,
      "n_negative": 1,
      "directional_bias": 0.0
    },
    {
      "ts": "2026-03-05T04:00:00",
      "raw": -0.8745901249349117,
      "smoothed": 0.026128714531660074,
      "n_posts": 1,
      "n_positive": 0,
      "n_negative": 1,
      "directional_bias": -1.0
    },
    {
      "ts": "2026-03-05T09:00:00",
      "raw": 0.6666372120380402,
      "smoothed": 0.1542304140329361,
      "n_posts": 1,
      "n_positive": 1,
      "n_negative": 0,
      "directional_bias": 1.0
    },
    {
      "ts": "2026-03-05T10:00:00",
      "raw": 0.0007534995675086975,
      "smoothed": 0.12353503113985063,
      "n_posts": 1,
      "n_positive": 1,
      "n_negative": 0,
      "directional_bias": 1.0
    },
    {
      "ts": "2026-03-05T15:00:00",
      "raw": 0.24932459617654484,
      "smoothed": 0.14869294414718948,
      "n_posts": 3,
      "n_positive": 2,
      "n_negative": 1,
      "directional_bias": 0.3333333333333333
    },
    {
      "ts": "2026-03-05T19:00:00",
      "raw": -0.599135858938098,
      "smoothed": -0.0008728164698680041,
      "n_posts": 1,
      "n_positive": 0,
      "n_negative": 1,
      "directional_bias": -1.0
    },
    {
      "ts": "2026-03-05T20:00:00",
      "raw": 0.03720247372984886,
      "smoothed": 0.006742241570075369,
      "n_posts": 1,
      "n_positive": 1,
      "n_negative": 0,
      "directional_bias": 1.0
    },
    {
      "ts": "2026-03-05T21:00:00",
      "raw": 0.005842407544453964,
      "smoothed": 0.0065622747649510885,
      "n_posts": 3,
      "n_positive": 2,
      "n_negative": 1,
      "directional_bias": 0.3333333333333333
    },
    {
      "ts": "2026-03-05T22:00:00",
      "raw": -0.005332935601472855,
      "smoothed": 0.0041832326916663,
      "n_posts": 1,
      "n_positive": 0,
      "n_negative": 1,
      "directional_bias": -1.0
    },
    {
      "ts": "2026-03-06T03:00:00",
      "raw": -0.7878317106515169,
      "smoothed": -0.7878317106515169,
      "n_posts": 1,
      "n_positive": 0,
      "n_negative": 1,
      "directional_bias": -1.0
    },
    {
      "ts": "2026-03-06T04:00:00",
      "raw": -0.4599958807229995,
      "smoothed": -0.7222645446658136,
      "n_posts": 1,
      "n_positive": 0,
      "n_negative": 1,
      "directional_bias": -1.0
    },
    {
      "ts": "2026-03-06T06:00:00",
      "raw": -0.031181668862700462,
      "smoothed": -0.584047969505191,
      "n_posts": 1,
      "n_positive": 0,
      "n_negative": 1,
      "directional_bias": -1.0
    },
    {
      "ts": "2026-03-06T07:00:00",
      "raw": -0.9461460905149579,
      "smoothed": -0.6564675937071445,
      "n_posts": 1,
      "n_positive": 0,
      "n_negative": 1,
      "directional_bias": -1.0
    },
    {
      "ts": "2026-03-06T10:00:00",
      "raw": -0.45089590549468994,
      "smoothed": -0.6153532560646535,
      "n_posts": 2,
      "n_positive": 1,
      "n_negative": 1,
      "directional_bias": 0.0
    },
    {
      "ts": "2026-03-06T11:00:00",
      "raw": -0.8953022100031376,
      "smoothed": -0.6713430468523504,
      "n_posts": 1,
      "n_positive": 0,
      "n_negative": 1,
      "directional_bias": -1.0
    },
    {
      "ts": "2026-03-06T12:00:00",
      "raw": -0.2638834677636624,
      "smoothed": -0.5898511310346128,
      "n_posts": 7,
      "n_positive": 3,
      "n_negative": 4,
      "directional_bias": -0.14285714285714285
    },
    {
      "ts": "2026-03-06T13:00:00",
      "raw": 0.0052504148334264755,
      "smoothed": -0.470830821861005,
      "n_posts": 1,
      "n_positive": 1,
      "n_negative": 0,
      "directional_bias": 1.0
    },
    {
      "ts": "2026-03-06T14:00:00",
      "raw": -0.5162682526279242,
      "smoothed": -0.47991830801438884,
      "n_posts": 4,
      "n_positive": 1,
      "n_negative": 3,
      "directional_bias": -0.5
    },
    {
      "ts": "2026-03-06T15:00:00",
      "raw": -0.4000589741586611,
      "smoothed": -0.4639464412432433,
      "n_posts": 5,
      "n_positive": 1,
      "n_negative": 4,
      "directional_bias": -0.6
    },
    {
      "ts": "2026-03-06T16:00:00",
      "raw": 0.23137490497902036,
      "smoothed": -0.3248821719987906,
      "n_posts": 4,
      "n_positive": 3,
      "n_negative": 1,
      "directional_bias": 0.5
    },
    {
      "ts": "2026-03-06T17:00:00",
      "raw": -0.36304852087050676,
      "smoothed": -0.33251544177313386,
      "n_posts": 2,
      "n_positive": 1,
      "n_negative": 1,
      "directional_bias": 0.0
    },
    {
      "ts": "2026-03-06T18:00:00",
      "raw": -0.19362798739563333,
      "smoothed": -0.3047379508976338,
      "n_posts": 2,
      "n_positive": 0,
      "n_negative": 2,
      "directional_bias": -1.0
    },
    {
      "ts": "2026-03-06T19:00:00",
      "raw": 0.18267012014985082,
      "smoothed": -0.20725633668813687,
      "n_posts": 2,
      "n_positive": 1,
      "n_negative": 1,
      "directional_bias": 0.0
    },
    {
      "ts": "2026-03-06T20:00:00",
      "raw": -0.14497192390263078,
      "smoothed": -0.19479945413103567,
      "n_posts": 6,
      "n_positive": 2,
      "n_negative": 4,
      "directional_bias": -0.3333333333333333
    },
    {
      "ts": "2026-03-06T21:00:00",
      "raw": -0.031012298648848264,
      "smoothed": -0.1620420230345982,
      "n_posts": 3,
      "n_positive": 2,
      "n_negative": 1,
      "directional_bias": 0.3333333333333333
    },
    {
      "ts": "2026-03-06T23:00:00",
      "raw": 0.5227003991603851,
      "smoothed": -0.02509353859560154,
      "n_posts": 1,
      "n_positive": 1,
      "n_negative": 0,
      "directional_bias": 1.0
    },
    {
      "ts": "2026-03-07T04:00:00",
      "raw": -0.768306914716959,
      "smoothed": -0.768306914716959,
      "n_posts": 1,
      "n_positive": 0,
      "n_negative": 1,
      "directional_bias": -1.0
    },
    {
      "ts": "2026-03-07T05:00:00",
      "raw": -0.0809623319655657,
      "smoothed": -0.6308379981666804,
      "n_posts": 2,
      "n_positive": 0,
      "n_negative": 2,
      "directional_bias": -1.0
    },
    {
      "ts": "2026-03-07T06:00:00",
      "raw": -0.5355396789188187,
      "smoothed": -0.6117783343171082,
      "n_posts": 3,
      "n_positive": 1,
      "n_negative": 2,
      "directional_bias": -0.3333333333333333
    },
    {
      "ts": "2026-03-07T07:00:00",
      "raw": -0.9556068098172545,
      "smoothed": -0.6805440294171374,
      "n_posts": 1,
      "n_positive": 0,
      "n_negative": 1,
      "directional_bias": -1.0
    },
    {
      "ts": "2026-03-07T09:00:00",
      "raw": 0.027140274643898017,
      "smoothed": -0.5390071686049304,
      "n_posts": 3,
      "n_positive": 3,
      "n_negative": 0,
      "directional_bias": 1.0
    },
    {
      "ts": "2026-03-07T10:00:00",
      "raw": -0.00140505221982797,
      "smoothed": -0.4314867453279099,
      "n_posts": 3,
      "n_positive": 1,
      "n_negative": 2,
      "directional_bias": -0.3333333333333333
    },
    {
      "ts": "2026-03-07T11:00:00",
      "raw": -0.9581366153433918,
      "smoothed": -0.5368167193310063,
      "n_posts": 1,
      "n_positive": 0,
      "n_negative": 1,
      "directional_bias": -1.0
    },
    {
      "ts": "2026-03-07T12:00:00",
      "raw": -0.018079298548400402,
      "smoothed": -0.43306923517448515,
      "n_posts": 2,
      "n_positive": 0,
      "n_negative": 2,
      "directional_bias": -1.0
    },
    {
      "ts": "2026-03-07T13:00:00",
      "raw": -0.025064049288630486,
      "smoothed": -0.35146819799731427,
      "n_posts": 1,
      "n_positive": 0,
      "n_negative": 1,
      "directional_bias": -1.0
    },
    {
      "ts": "2026-03-07T14:00:00",
      "raw": 0.018864747136831284,
      "smoothed": -0.27740160897048516,
      "n_posts": 1,
      "n_positive": 1,
      "n_negative": 0,
      "directional_bias": 1.0
    },
    {
      "ts": "2026-03-07T15:00:00",
      "raw": -0.13566804751753805,
      "smoothed": -0.24905489667989578,
      "n_posts": 8,
      "n_positive": 5,
      "n_negative": 3,
      "directional_bias": 0.25
    },
    {
      "ts": "2026-03-07T16:00:00",
      "raw": -0.042580359149724245,
      "smoothed": -0.2077599891738615,
      "n_posts": 3,
      "n_positive": 0,
      "n_negative": 3,
      "directional_bias": -1.0
    },
    {
      "ts": "2026-03-07T17:00:00",
      "raw": -0.046876881809698207,
      "smoothed": -0.17558336770102884,
      "n_posts": 8,
      "n_positive": 6,
      "n_negative": 2,
      "directional_bias": 0.5
    },
    {
      "ts": "2026-03-07T18:00:00",
      "raw": -0.14642073789282758,
      "smoothed": -0.1697508417393886,
      "n_posts": 6,
      "n_positive": 3,
      "n_negative": 3,
      "directional_bias": 0.0
    },
    {
      "ts": "2026-03-07T19:00:00",
      "raw": -0.5024262510240077,
      "smoothed": -0.23628592359631245,
      "n_posts": 5,
      "n_positive": 0,
      "n_negative": 5,
      "directional_bias": -1.0
    },
    {
      "ts": "2026-03-07T20:00:00",
      "raw": 0.0582692010793835,
      "smoothed": -0.17737489866117326,
      "n_posts": 4,
      "n_positive": 3,
      "n_negative": 1,
      "directional_bias": 0.5
    },
    {
      "ts": "2026-03-07T21:00:00",
      "raw": -0.059061992036945676,
      "smoothed": -0.15371231733632773,
      "n_posts": 3,
      "n_positive": 1,
      "n_negative": 2,
      "directional_bias": -0.3333333333333333
    },
    {
      "ts": "2026-03-07T22:00:00",
      "raw": -0.2316456117356817,
      "smoothed": -0.16929897621619855,
      "n_posts": 3,
      "n_positive": 2,
      "n_negative": 1,
      "directional_bias": 0.3333333333333333
    },
    {
      "ts": "2026-03-07T23:00:00",
      "raw": -0.06237940676510334,
      "smoothed": -0.1479150623259795,
      "n_posts": 2,
      "n_positive": 1,
      "n_negative": 1,
      "directional_bias": 0.0
    },
    {
      "ts": "2026-03-08T00:00:00",
      "raw": -0.14186576618389649,
      "smoothed": -0.14186576618389649,
      "n_posts": 2,
      "n_positive": 0,
      "n_negative": 2,
      "directional_bias": -1.0
    },
    {
      "ts": "2026-03-08T01:00:00",
      "raw": 0.027997825294733044,
      "smoothed": -0.10789304788817058,
      "n_posts": 1,
      "n_positive": 1,
      "n_negative": 0,
      "directional_bias": 1.0
    },
    {
      "ts": "2026-03-08T02:00:00",
      "raw": 0.06220379564911127,
      "smoothed": -0.07387367918071422,
      "n_posts": 3,
      "n_positive": 2,
      "n_negative": 1,
      "directional_bias": 0.3333333333333333
    },
    {
      "ts": "2026-03-08T03:00:00",
      "raw": 0.012796808034181595,
      "smoothed": -0.05653958173773506,
      "n_posts": 3,
      "n_positive": 3,
      "n_negative": 0,
      "directional_bias": 1.0
    },
    {
      "ts": "2026-03-08T04:00:00",
      "raw": -0.17529916390776634,
      "smoothed": -0.08029149817174133,
      "n_posts": 1,
      "n_positive": 0,
      "n_negative": 1,
      "directional_bias": -1.0
    }
  ]
}