{
  "granularity": "hourly",
  "data": [
    {
      "ts": "2026-03-08T10:00:00",
      "raw": 0.016804253682494164,
      "smoothed": 0.016804253682494164,
      "n_posts": 1,
      "n_positive": 1,
      "n_negative": 0,
      "directional_bias": 1.0
    },
    {
      "ts": "2026-03-08T16:00:00",
      "raw": -0.9318076809868217,
      "smoothed": -0.172918133251369,
      "n_posts": 1,
      "n_positive": 0,
      "n_negative": 1,
      "directional_bias": -1.0
    },
    {
      "ts": "2026-03-09T09:00:00",
      "raw": 0.05838437844067812,
      "smoothed": 0.05838437844067812,
      "n_posts": 1,
      "n_positive": 1,
      "n_negative": 0,
      "directional_bias": 1.0
    },
    {
      "ts": "2026-03-09T10:00:00",
      "raw": 0.022010015323758125,
      "smoothed": 0.05110950581729412,
      "n_posts": 1,
      "n_positive": 1,
      "n_negative": 0,
      "directional_bias": 1.0
    },
    {
      "ts": "2026-03-09T12:00:00",
      "raw": -0.030405920337546955,
      "smoothed": 0.03480642058632591,
      "n_posts": 2,
      "n_positive": 0,
      "n_negative": 2,
      "directional_bias": -1.0
    },
    {
      "ts": "2026-03-09T17:00:00",
      "raw": -0.017829056829214096,
      "smoothed": 0.024279325103217907,
      "n_posts": 1,
      "n_positive": 0,
      "n_negative": 1,
      "directional_bias": -1.0
    },
    {
      "ts": "2026-03-09T20:00:00",
      "raw": 0.46252916753292084,
      "smoothed": 0.1119292935891585,
      "n_posts": 1,
      "n_positive": 1,
      "n_negative": 0,
      "directional_bias": 1.0
    },
    {
      "ts": "2026-03-09T21:00:00",
      "raw": -0.0590674877166748,
      "smoothed": 0.07772993732799185,
      "n_posts": 1,
      "n_positive": 0,
      "n_negative": 1,
      "directional_bias": -1.0
    },
    {
      "ts": "2026-03-10T17:00:00",
      "raw": 0.05633416399359703,
      "smoothed": 0.05633416399359703,
      "n_posts": 1,
      "n_positive": 1,
      "n_negative": 0,
      "directional_bias": 1.0
    },
    {
      "ts": "2026-03-10T19:00:00",
      "raw": 0.023184845224022865,
      "smoothed": 0.049704300239682205,
      "n_posts": 1,
      "n_positive": 1,
      "n_negative": 0,
      "directional_bias": 1.0
    },
    {
      "ts": "2026-03-10T21:00:00",
      "raw": 0.29717678390443325,
      "smoothed": 0.09919879697263242,
      "n_posts": 3,
      "n_positive": 3,
      "n_negative": 0,
      "directional_bias": 1.0
    },
    {
      "ts": "2026-03-11T05:00:00",
      "raw": 0.024127662181854248,
      "smoothed": 0.024127662181854248,
      "n_posts": 1,
      "n_positive": 1,
      "n_negative": 0,
      "directional_bias": 1.0
    },
    {
      "ts": "2026-03-11T17:00:00",
      "raw": 0.061092376708984375,
      "smoothed": 0.03152060508728027,
      "n_posts": 1,
      "n_positive": 1,
      "n_negative": 0,
      "directional_bias": 1.0
    },
    {
      "ts": "2026-03-11T18:00:00",
      "raw": 0.02870911918580532,
      "smoothed": 0.030958307906985283,
      "n_posts": 1,
      "n_positive": 1,
      "n_negative": 0,
      "directional_bias": 1.0
    },
    {
      "ts": "2026-03-11T23:00:00",
      "raw": 0.04776407778263092,
      "smoothed": 0.03431946188211441,
      "n_posts": 1,
      "n_positive": 1,
      "n_negative": 0,
      "directional_bias": 1.0
    },
    {
      "ts": "2026-03-12T09:00:00",
      "raw": 0.0002284087240695953,
      "smoothed": 0.0002284087240695953,
      "n_posts": 1,
      "n_positive": 1,
      "n_negative": 0,
      "directional_bias": 1.0
    },
    {
      "ts": "2026-03-12T10:00:00",
      "raw": 0.0432346910238266,
      "smoothed": 0.008829665184020997,
      "n_posts": 1,
      "n_positive": 1,
      "n_negative": 0,
      "directional_bias": 1.0
    },
    {
      "ts": "2026-03-12T11:00:00",
      "raw": 0.8551234863698481,
      "smoothed": 0.1780884294211864,
      "n_posts": 1,
      "n_positive": 1,
      "n_negative": 0,
      "directional_bias": 1.0
    },
    {
      "ts": "2026-03-12T14:00:00",
      "raw": 0.011731502953274497,
      "smoothed": 0.14481704412760404,
      "n_posts": 5,
      "n_positive": 3,
      "n_negative": 2,
      "directional_bias": 0.2
    },
    {
      "ts": "2026-03-12T15:00:00",
      "raw": -0.7484221160411835,
      "smoothed": -0.033830787906153445,
      "n_posts": 1,
      "n_positive": 0,
      "n_negative": 1,
      "directional_bias": -1.0
    },
    {
      "ts": "2026-03-12T16:00:00",
      "raw": -0.390565499663353,
      "smoothed": -0.10517773025759337,
      "n_posts": 2,
      "n_positive": 1,
      "n_negative": 1,
      "directional_bias": 0.0
    },
    {
      "ts": "2026-03-12T17:00:00",
      "raw": 0.15197890507988632,
      "smoothed": -0.05374640319009744,
      "n_posts": 4,
      "n_positive": 4,
      "n_negative": 0,
      "directional_bias": 1.0
    },
    {
      "ts": "2026-03-12T18:00:00",
      "raw": 0.05957409646362066,
      "smoothed": -0.031082303259353825,
      "n_posts": 1,
      "n_positive": 1,
      "n_negative": 0,
      "directional_bias": 1.0
    },
    {
      "ts": "2026-03-12T20:00:00",
      "raw": -0.12551921280100942,
      "smoothed": -0.04996968516768495,
      "n_posts": 4,
      "n_positive": 1,
      "n_negative": 3,
      "directional_bias": -0.5
    },
    {
      "ts": "2026-03-12T22:00:00",
      "raw": -0.07442760467529297,
      "smoothed": -0.054861269069206554,
      "n_posts": 1,
      "n_positive": 0,
      "n_negative": 1,
      "directional_bias": -1.0
    },
    {
      "ts": "2026-03-12T23:00:00",
      "raw": 0.014631003141403198,
      "smoothed": -0.04096281462708461,
      "n_posts": 1,
      "n_positive": 1,
      "n_negative": 0,
      "directional_bias": 1.0
    },
    {
      "ts": "2026-03-13T00:00:00",
      "raw": 0.878536906093359,
      "smoothed": 0.878536906093359,
      "n_posts": 1,
      "n_positive": 1,
      "n_negative": 0,
      "directional_bias": 1.0
    },
    {
      "ts": "2026-03-13T03:00:00",
      "raw": 0.2771278516772915,
      "smoothed": 0.7582550952101454,
      "n_posts": 3,
      "n_positive": 2,
      "n_negative": 1,
      "directional_bias": 0.3333333333333333
    },
    {
      "ts": "2026-03-13T05:00:00",
      "raw": 0.06625646073371172,
      "smoothed": 0.6198553683148588,
      "n_posts": 1,
      "n_positive": 1,
      "n_negative": 0,
      "directional_bias": 1.0
    },
    {
      "ts": "2026-03-13T07:00:00",
      "raw": -0.049829237163066864,
      "smoothed": 0.4859184472192737,
      "n_posts": 1,
      "n_positive": 0,
      "n_negative": 1,
      "directional_bias": -1.0
    },
    {
      "ts": "2026-03-13T08:00:00",
      "raw": 0.0808399273082614,
      "smoothed": 0.40490274323707126,
      "n_posts": 2,
      "n_positive": 2,
      "n_negative": 0,
      "directional_bias": 1.0
    },
    {
      "ts": "2026-03-13T09:00:00",
      "raw": 0.7592581585049629,
      "smoothed": 0.4757738262906496,
      "n_posts": 1,
      "n_positive": 1,
      "n_negative": 0,
      "directional_bias": 1.0
    },
    {
      "ts": "2026-03-13T10:00:00",
      "raw": 0.8379323929548265,
      "smoothed": 0.5482055396234851,
      "n_posts": 1,
      "n_positive": 1,
      "n_negative": 0,
      "directional_bias": 1.0
    },
    {
      "ts": "2026-03-13T11:00:00",
      "raw": 0.22642143536359072,
      "smoothed": 0.4838487187715062,
      "n_posts": 1,
      "n_positive": 1,
      "n_negative": 0,
      "directional_bias": 1.0
    },
    {
      "ts": "2026-03-13T12:00:00",
      "raw": 0.38503130525350565,
      "smoothed": 0.46408523606790614,
      "n_posts": 2,
      "n_positive": 1,
      "n_negative": 1,
      "directional_bias": 0.0
    },
    {
      "ts": "2026-03-13T13:00:00",
      "raw": 0.10671941656619312,
      "smoothed": 0.39261207216756355,
      "n_posts": 2,
      "n_positive": 1,
      "n_negative": 1,
      "directional_bias": 0.0
    },
    {
      "ts": "2026-03-13T14:00:00",
      "raw": 0.3317292101424315,
      "smoothed": 0.38043549976253715,
      "n_posts": 5,
      "n_positive": 5,
      "n_negative": 0,
      "directional_bias": 1.0
    },
    {
      "ts": "2026-03-13T15:00:00",
      "raw": 0.24623535307390348,
      "smoothed": 0.35359547042481043,
      "n_posts": 7,
      "n_positive": 6,
      "n_negative": 1,
      "directional_bias": 0.7142857142857143
    },
    {
      "ts": "2026-03-13T16:00:00",
      "raw": -0.23573910281993452,
      "smoothed": 0.23572855577586144,
      "n_posts": 4,
      "n_positive": 1,
      "n_negative": 3,
      "directional_bias": -0.5
    },
    {
      "ts": "2026-03-13T17:00:00",
      "raw": 0.21789545069138208,
      "smoothed": 0.23216193475896557,
      "n_posts": 3,
      "n_positive": 3,
      "n_negative": 0,
      "directional_bias": 1.0
    },
    {
      "ts": "2026-03-13T18:00:00",
      "raw": 0.030264196339352383,
      "smoothed": 0.19178238707504294,
      "n_posts": 5,
      "n_positive": 3,
      "n_negative": 2,
      "directional_bias": 0.2
    },
    {
      "ts": "2026-03-13T19:00:00",
      "raw": 0.439509532329711,
      "smoothed": 0.24132781612597656,
      "n_posts": 2,
      "n_positive": 1,
      "n_negative": 1,
      "directional_bias": 0.0
    },
    {
      "ts": "2026-03-13T20:00:00",
      "raw": 0.9305988587439061,
      "smoothed": 0.3791820246495625,
      "n_posts": 1,
      "n_positive": 1,
      "n_negative": 0,
      "directional_bias": 1.0
    },
    {
      "ts": "2026-03-13T21:00:00",
      "raw": -0.1663226073142141,
      "smoothed": 0.2700810982568072,
      "n_posts": 4,
      "n_positive": 2,
      "n_negative": 2,
      "directional_bias": 0.0
    },
    {
      "ts": "2026-03-13T22:00:00",
      "raw": -0.2970312926918268,
      "smoothed": 0.1566586200670804,
      "n_posts": 2,
      "n_positive": 1,
      "n_negative": 1,
      "directional_bias": 0.0
    },
    {
      "ts": "2026-03-14T00:00:00",
      "raw": 0.10073306690901518,
      "smoothed": 0.10073306690901518,
      "n_posts": 3,
      "n_positive": 3,
      "n_negative": 0,
      "directional_bias": 1.0
    },
    {
      "ts": "2026-03-14T01:00:00",
      "raw": 0.9127380922436714,
      "smoothed": 0.26313407197594646,
      "n_posts": 1,
      "n_positive": 1,
      "n_negative": 0,
      "directional_bias": 1.0
    },
    {
      "ts": "2026-03-14T02:00:00",
      "raw": 0.11155648889212776,
      "smoothed": 0.23281855535918272,
      "n_posts": 5,
      "n_positive": 2,
      "n_negative": 3,
      "directional_bias": -0.2
    },
    {
      "ts": "2026-03-14T03:00:00",
      "raw": 0.1331029273569584,
      "smoothed": 0.21287542975873786,
      "n_posts": 1,
      "n_positive": 1,
      "n_negative": 0,
      "directional_bias": 1.0
    },
    {
      "ts": "2026-03-14T04:00:00",
      "raw": -0.554772824048996,
      "smoothed": 0.059345778997191095,
      "n_posts": 1,
      "n_positive": 0,
      "n_negative": 1,
      "directional_bias": -1.0
    },
    {
      "ts": "2026-03-14T06:00:00",
      "raw": -0.004033840261399744,
      "smoothed": 0.04666985514547293,
      "n_posts": 2,
      "n_positive": 1,
      "n_negative": 1,
      "directional_bias": 0.0
    },
    {
      "ts": "2026-03-14T07:00:00",
      "raw": 0.45917276326905593,
      "smoothed": 0.12917043677018952,
      "n_posts": 2,
      "n_positive": 1,
      "n_negative": 1,
      "directional_bias": 0.0
    },
    {
      "ts": "2026-03-14T08:00:00",
      "raw": 0.5376956750723448,
      "smoothed": 0.2108754844306206,
      "n_posts": 2,
      "n_positive": 2,
      "n_negative": 0,
      "directional_bias": 1.0
    },
    {
      "ts": "2026-03-14T09:00:00",
      "raw": -0.31225083395838743,
      "smoothed": 0.106250220752819,
      "n_posts": 3,
      "n_positive": 1,
      "n_negative": 2,
      "directional_bias": -0.3333333333333333
    },
    {
      "ts": "2026-03-14T11:00:00",
      "raw": -0.07486495779206354,
      "smoothed": 0.07002718504384249,
      "n_posts": 6,
      "n_positive": 3,
      "n_negative": 3,
      "directional_bias": 0.0
    },
    {
      "ts": "2026-03-14T12:00:00",
      "raw": -0.0871665465335051,
      "smoothed": 0.038588438728372976,
      "n_posts": 6,
      "n_positive": 3,
      "n_negative": 3,
      "directional_bias": 0.0
    },
    {
      "ts": "2026-03-14T14:00:00",
      "raw": 0.2784721687799547,
      "smoothed": 0.08656518473868932,
      "n_posts": 7,
      "n_positive": 6,
      "n_negative": 1,
      "directional_bias": 0.7142857142857143
    },
    {
      "ts": "2026-03-14T15:00:00",
      "raw": -0.04250204749405382,
      "smoothed": 0.06075173829214069,
      "n_posts": 5,
      "n_positive": 2,
      "n_negative": 3,
      "directional_bias": -0.2
    },
    {
      "ts": "2026-03-14T16:00:00",
      "raw": 0.012360821054740385,
      "smoothed": 0.05107355484466063,
      "n_posts": 2,
      "n_positive": 2,
      "n_negative": 0,
      "directional_bias": 1.0
    },
    {
      "ts": "2026-03-14T17:00:00",
      "raw": 0.08163583933793266,
      "smoothed": 0.05718601174331504,
      "n_posts": 5,
      "n_positive": 3,
      "n_negative": 2,
      "directional_bias": 0.2
    },
    {
      "ts": "2026-03-14T18:00:00",
      "raw": -0.0813682892670234,
      "smoothed": 0.029475151541247354,
      "n_posts": 3,
      "n_positive": 1,
      "n_negative": 2,
      "directional_bias": -0.3333333333333333
    },
    {
      "ts": "2026-03-14T19:00:00",
      "raw": -0.6002579815685749,
      "smoothed": -0.0964714750807171,
      "n_posts": 2,
      "n_positive": 0,
      "n_negative": 2,
      "directional_bias": -1.0
    }
  ]
}