{
  "day": "2026-02-12",
  "positives": [
    {
      "title": "Midnight (Cardano partner chain) proposes \u201cconfidential by default\u201d TXs with selective ZK disclosure",
      "polarity": 0.06641950272023678,
      "ts": "2026-02-12T05:59:25",
      "source": "r/CryptoTechnology",
      "url": "https://www.reddit.com/r/CryptoTechnology/comments/1r2lmvw/midnight_cardano_partner_chain_proposes/"
    }
  ],
  "negatives": [
    {
      "title": "The Best Way To Squander an ETH Bear Market",
      "polarity": -0.03910064324736595,
      "ts": "2026-02-12T10:09:11",
      "source": "r/ethtrader",
      "url": "https://www.reddit.com/r/ethtrader/comments/1r2pnq0/the_best_way_to_squander_an_eth_bear_market/"
    }
  ]
}