{
  "granularity": "1h",
  "updated": "2026-03-16T01:09:32.612797Z",
  "candles": [
    {
      "ts": "2026-03-09T02:00:00Z",
      "open": 66194.01,
      "high": 66720.64,
      "low": 65941.83,
      "close": 66533.43,
      "volume": 390.55138812,
      "ema9": null,
      "ema21": null,
      "ema50": null,
      "vwap": 66398.6333,
      "rsi14": null,
      "atr14": null,
      "avg_volume": null
    },
    {
      "ts": "2026-03-09T03:00:00Z",
      "open": 66533.44,
      "high": 67668.72,
      "low": 66507.45,
      "close": 67201.76,
      "volume": 492.28023552,
      "ema9": null,
      "ema21": null,
      "ema50": null,
      "vwap": 66804.211,
      "rsi14": null,
      "atr14": null,
      "avg_volume": null
    },
    {
      "ts": "2026-03-09T04:00:00Z",
      "open": 67200.76,
      "high": 67603.0,
      "low": 67102.1,
      "close": 67150.63,
      "volume": 470.84875582,
      "ema9": null,
      "ema21": null,
      "ema50": null,
      "vwap": 66971.5278,
      "rsi14": null,
      "atr14": null,
      "avg_volume": null
    },
    {
      "ts": "2026-03-09T05:00:00Z",
      "open": 67150.63,
      "high": 68055.63,
      "low": 67112.35,
      "close": 67901.55,
      "volume": 373.62996771,
      "ema9": null,
      "ema21": null,
      "ema50": null,
      "vwap": 67126.9047,
      "rsi14": null,
      "atr14": null,
      "avg_volume": null
    },
    {
      "ts": "2026-03-09T06:00:00Z",
      "open": 67901.55,
      "high": 67927.63,
      "low": 67228.02,
      "close": 67255.0,
      "volume": 177.93203706,
      "ema9": null,
      "ema21": null,
      "ema50": null,
      "vwap": 67158.9669,
      "rsi14": null,
      "atr14": null,
      "avg_volume": null
    },
    {
      "ts": "2026-03-09T07:00:00Z",
      "open": 67255.81,
      "high": 67556.0,
      "low": 66871.39,
      "close": 67533.14,
      "volume": 243.32846519,
      "ema9": null,
      "ema21": null,
      "ema50": null,
      "vwap": 67177.2241,
      "rsi14": null,
      "atr14": null,
      "avg_volume": null
    },
    {
      "ts": "2026-03-09T08:00:00Z",
      "open": 67535.77,
      "high": 67920.57,
      "low": 67377.98,
      "close": 67806.0,
      "volume": 226.3460183,
      "ema9": null,
      "ema21": null,
      "ema50": null,
      "vwap": 67227.1928,
      "rsi14": null,
      "atr14": null,
      "avg_volume": null
    },
    {
      "ts": "2026-03-09T09:00:00Z",
      "open": 67806.0,
      "high": 68457.47,
      "low": 67555.34,
      "close": 67974.97,
      "volume": 350.5276324,
      "ema9": null,
      "ema21": null,
      "ema50": null,
      "vwap": 67326.062,
      "rsi14": null,
      "atr14": null,
      "avg_volume": null
    },
    {
      "ts": "2026-03-09T10:00:00Z",
      "open": 67974.98,
      "high": 68077.96,
      "low": 67540.6,
      "close": 67592.67,
      "volume": 265.02408113,
      "ema9": 67438.7944,
      "ema21": null,
      "ema50": null,
      "vwap": 67362.4873,
      "rsi14": null,
      "atr14": null,
      "avg_volume": null
    },
    {
      "ts": "2026-03-09T11:00:00Z",
      "open": 67592.67,
      "high": 67847.02,
      "low": 67326.48,
      "close": 67755.33,
      "volume": 162.69185096,
      "ema9": 67502.1016,
      "ema21": null,
      "ema50": null,
      "vwap": 67376.9579,
      "rsi14": null,
      "atr14": null,
      "avg_volume": null
    },
    {
      "ts": "2026-03-09T12:00:00Z",
      "open": 67755.33,
      "high": 68351.33,
      "low": 67741.44,
      "close": 68150.04,
      "volume": 370.10538442,
      "ema9": 67631.6892,
      "ema21": null,
      "ema50": null,
      "vwap": 67450.9081,
      "rsi14": null,
      "atr14": null,
      "avg_volume": null
    },
    {
      "ts": "2026-03-09T13:00:00Z",
      "open": 68150.05,
      "high": 69324.94,
      "low": 68125.21,
      "close": 68988.3,
      "volume": 1370.17135486,
      "ema9": 67903.0114,
      "ema21": null,
      "ema50": null,
      "vwap": 67832.245,
      "rsi14": null,
      "atr14": null,
      "avg_volume": null
    },
    {
      "ts": "2026-03-09T14:00:00Z",
      "open": 68983.2,
      "high": 69500.0,
      "low": 68702.95,
      "close": 69172.01,
      "volume": 1696.48071323,
      "ema9": 68156.8111,
      "ema21": null,
      "ema50": null,
      "vwap": 68165.043,
      "rsi14": null,
      "atr14": null,
      "avg_volume": null
    },
    {
      "ts": "2026-03-09T15:00:00Z",
      "open": 69172.01,
      "high": 69288.0,
      "low": 68735.2,
      "close": 68885.47,
      "volume": 1078.34503166,
      "ema9": 68302.5429,
      "ema21": null,
      "ema50": null,
      "vwap": 68278.1772,
      "rsi14": null,
      "atr14": null,
      "avg_volume": null
    },
    {
      "ts": "2026-03-09T16:00:00Z",
      "open": 68887.07,
      "high": 69248.48,
      "low": 68647.62,
      "close": 68968.04,
      "volume": 816.35071537,
      "ema9": 68435.6423,
      "ema21": null,
      "ema50": null,
      "vwap": 68343.2704,
      "rsi14": 74.0036,
      "atr14": 732.33,
      "avg_volume": null
    },
    {
      "ts": "2026-03-09T17:00:00Z",
      "open": 68968.04,
      "high": 69111.12,
      "low": 68252.14,
      "close": 68611.96,
      "volume": 581.24004352,
      "ema9": 68470.9059,
      "ema21": null,
      "ema50": null,
      "vwap": 68363.4748,
      "rsi14": 68.6132,
      "atr14": 741.3764,
      "avg_volume": null
    },
    {
      "ts": "2026-03-09T18:00:00Z",
      "open": 68611.96,
      "high": 68728.27,
      "low": 68238.72,
      "close": 68365.46,
      "volume": 644.18449262,
      "ema9": 68449.8167,
      "ema21": null,
      "ema50": null,
      "vwap": 68368.827,
      "rsi14": 65.0792,
      "atr14": 723.3888,
      "avg_volume": null
    },
    {
      "ts": "2026-03-09T19:00:00Z",
      "open": 68365.47,
      "high": 69543.0,
      "low": 68365.47,
      "close": 69012.12,
      "volume": 1321.66878092,
      "ema9": 68562.2773,
      "ema21": null,
      "ema50": null,
      "vwap": 68441.2742,
      "rsi14": 69.5151,
      "atr14": 755.8282,
      "avg_volume": null
    },
    {
      "ts": "2026-03-09T20:00:00Z",
      "open": 69012.13,
      "high": 69179.32,
      "low": 68767.93,
      "close": 68973.85,
      "volume": 623.97226341,
      "ema9": 68644.5919,
      "ema21": null,
      "ema50": null,
      "vwap": 68469.777,
      "rsi14": 68.9569,
      "atr14": 731.2255,
      "avg_volume": null
    },
    {
      "ts": "2026-03-09T21:00:00Z",
      "open": 68973.84,
      "high": 69122.99,
      "low": 68664.97,
      "close": 68922.05,
      "volume": 194.57134875,
      "ema9": 68700.0835,
      "ema21": null,
      "ema50": null,
      "vwap": 68476.8957,
      "rsi14": 68.159,
      "atr14": 711.7108,
      "avg_volume": 592.5125
    },
    {
      "ts": "2026-03-09T22:00:00Z",
      "open": 68922.04,
      "high": 69051.91,
      "low": 68602.81,
      "close": 68640.11,
      "volume": 272.74849792,
      "ema9": 68688.0888,
      "ema21": 68161.6138,
      "ema50": null,
      "vwap": 68483.3763,
      "rsi14": 63.8298,
      "atr14": 692.9529,
      "avg_volume": 586.6224
    },
    {
      "ts": "2026-03-09T23:00:00Z",
      "open": 68645.39,
      "high": 68710.25,
      "low": 68375.01,
      "close": 68432.17,
      "volume": 260.75144326,
      "ema9": 68636.905,
      "ema21": 68186.2098,
      "ema50": null,
      "vwap": 68483.8487,
      "rsi14": 60.7643,
      "atr14": 667.402,
      "avg_volume": 575.0459
    },
    {
      "ts": "2026-03-10T00:00:00Z",
      "open": 68432.16,
      "high": 69304.54,
      "low": 68383.5,
      "close": 69160.19,
      "volume": 294.49938021,
      "ema9": 68741.562,
      "ema21": 68274.7535,
      "ema50": null,
      "vwap": 68949.41,
      "rsi14": 66.7797,
      "atr14": 685.519,
      "avg_volume": 566.2285
    },
    {
      "ts": "2026-03-10T01:00:00Z",
      "open": 69157.93,
      "high": 69396.43,
      "low": 68796.23,
      "close": 69265.98,
      "volume": 210.28241553,
      "ema9": 68846.4456,
      "ema21": 68364.865,
      "ema50": null,
      "vwap": 69034.1717,
      "rsi14": 67.5581,
      "atr14": 679.4247,
      "avg_volume": 558.0611
    },
    {
      "ts": "2026-03-10T02:00:00Z",
      "open": 69254.53,
      "high": 70603.99,
      "low": 69094.6,
      "close": 70279.04,
      "volume": 494.21964817,
      "ema9": 69132.9645,
      "ema21": 68538.8809,
      "ema50": null,
      "vwap": 69508.2912,
      "rsi14": 73.8715,
      "atr14": 738.708,
      "avg_volume": 573.8755
    },
    {
      "ts": "2026-03-10T03:00:00Z",
      "open": 70279.04,
      "high": 70378.0,
      "low": 69358.16,
      "close": 69430.34,
      "volume": 420.13917592,
      "ema9": 69192.4396,
      "ema21": 68619.9226,
      "ema50": null,
      "vwap": 69571.6094,
      "rsi14": 62.8387,
      "atr14": 758.7888,
      "avg_volume": 582.716
    },
    {
      "ts": "2026-03-10T04:00:00Z",
      "open": 69429.42,
      "high": 70145.39,
      "low": 69429.42,
      "close": 70073.74,
      "volume": 204.34471488,
      "ema9": 69368.6997,
      "ema21": 68752.0878,
      "ema50": null,
      "vwap": 69610.7846,
      "rsi14": 66.8774,
      "atr14": 755.7304,
      "avg_volume": 581.6159
    },
    {
      "ts": "2026-03-10T05:00:00Z",
      "open": 70075.0,
      "high": 70368.01,
      "low": 69888.01,
      "close": 69973.8,
      "volume": 173.29089535,
      "ema9": 69489.7197,
      "ema21": 68863.1526,
      "ema50": null,
      "vwap": 69655.7111,
      "rsi14": 65.6833,
      "atr14": 736.0353,
      "avg_volume": 572.7541
    },
    {
      "ts": "2026-03-10T06:00:00Z",
      "open": 69973.8,
      "high": 70193.76,
      "low": 69760.09,
      "close": 69919.17,
      "volume": 185.49615443,
      "ema9": 69575.6098,
      "ema21": 68959.1542,
      "ema50": null,
      "vwap": 69683.9679,
      "rsi14": 65.0,
      "atr14": 714.4378,
      "avg_volume": 568.7777
    },
    {
      "ts": "2026-03-10T07:00:00Z",
      "open": 69918.0,
      "high": 70534.67,
      "low": 69834.97,
      "close": 70413.22,
      "volume": 349.115034,
      "ema9": 69743.1318,
      "ema21": 69091.342,
      "ema50": null,
      "vwap": 69770.369,
      "rsi14": 68.2196,
      "atr14": 713.3851,
      "avg_volume": 578.0989
    },
    {
      "ts": "2026-03-10T08:00:00Z",
      "open": 70415.27,
      "high": 71089.9,
      "low": 70379.99,
      "close": 70692.97,
      "volume": 408.44412824,
      "ema9": 69933.0995,
      "ema21": 69236.9445,
      "ema50": null,
      "vwap": 69912.0786,
      "rsi14": 69.9076,
      "atr14": 713.1369,
      "avg_volume": 580.0158
    },
    {
      "ts": "2026-03-10T09:00:00Z",
      "open": 70699.98,
      "high": 71305.04,
      "low": 70660.23,
      "close": 71067.99,
      "volume": 404.25869937,
      "ema9": 70160.0776,
      "ema21": 69403.4032,
      "ema50": null,
      "vwap": 70053.3861,
      "rsi14": 72.0507,
      "atr14": 708.2564,
      "avg_volume": 531.7202
    },
    {
      "ts": "2026-03-10T10:00:00Z",
      "open": 71067.99,
      "high": 71096.33,
      "low": 70677.5,
      "close": 70777.62,
      "volume": 278.58966181,
      "ema9": 70283.5861,
      "ema21": 69528.332,
      "ema50": null,
      "vwap": 70118.266,
      "rsi14": 68.0118,
      "atr14": 687.5831,
      "avg_volume": 460.8256
    },
    {
      "ts": "2026-03-10T11:00:00Z",
      "open": 70777.62,
      "high": 70882.59,
      "low": 70547.51,
      "close": 70605.18,
      "volume": 263.70621737,
      "ema9": 70347.9048,
      "ema21": 69626.2273,
      "ema50": null,
      "vwap": 70158.3372,
      "rsi14": 65.658,
      "atr14": 662.4043,
      "avg_volume": 420.0937
    },
    {
      "ts": "2026-03-10T12:00:00Z",
      "open": 70605.17,
      "high": 70642.8,
      "low": 70305.84,
      "close": 70537.56,
      "volume": 487.83174558,
      "ema9": 70385.8359,
      "ema21": 69709.0757,
      "ema50": null,
      "vwap": 70197.729,
      "rsi14": 64.7122,
      "atr14": 639.1583,
      "avg_volume": 403.6677
    },
    {
      "ts": "2026-03-10T13:00:00Z",
      "open": 70539.56,
      "high": 70944.12,
      "low": 69710.0,
      "close": 69920.2,
      "volume": 834.04662395,
      "ema9": 70292.7087,
      "ema21": 69728.2688,
      "ema50": null,
      "vwap": 70196.6817,
      "rsi14": 56.684,
      "atr14": 681.6555,
      "avg_volume": 416.3081
    },
    {
      "ts": "2026-03-10T14:00:00Z",
      "open": 69920.2,
      "high": 71538.46,
      "low": 69275.01,
      "close": 71481.24,
      "volume": 1607.22628374,
      "ema9": 70530.415,
      "ema21": 69887.6298,
      "ema50": null,
      "vwap": 70334.7305,
      "rsi14": 67.6221,
      "atr14": 794.6409,
      "avg_volume": 464.4602
    },
    {
      "ts": "2026-03-10T15:00:00Z",
      "open": 71481.24,
      "high": 71800.0,
      "low": 70920.0,
      "close": 71370.62,
      "volume": 1113.29935709,
      "ema9": 70698.456,
      "ema21": 70022.4471,
      "ema50": null,
      "vwap": 70482.9261,
      "rsi14": 66.3436,
      "atr14": 800.7379,
      "avg_volume": 454.0417
    },
    {
      "ts": "2026-03-10T16:00:00Z",
      "open": 71370.62,
      "high": 71730.94,
      "low": 70962.9,
      "close": 71291.52,
      "volume": 1161.64159803,
      "ema9": 70817.0688,
      "ema21": 70137.8174,
      "ema50": null,
      "vwap": 70593.4044,
      "rsi14": 65.3916,
      "atr14": 798.4024,
      "avg_volume": 480.9252
    },
    {
      "ts": "2026-03-10T17:00:00Z",
      "open": 71290.91,
      "high": 71485.0,
      "low": 70534.97,
      "close": 70891.96,
      "volume": 972.22319459,
      "ema9": 70832.047,
      "ema21": 70206.3758,
      "ema50": null,
      "vwap": 70630.5912,
      "rsi14": 60.6565,
      "atr14": 809.2329,
      "avg_volume": 519.8077
    },
    {
      "ts": "2026-03-10T18:00:00Z",
      "open": 70891.97,
      "high": 70942.01,
      "low": 69893.7,
      "close": 70026.99,
      "volume": 814.74865182,
      "ema9": 70671.0356,
      "ema21": 70190.068,
      "ema50": null,
      "vwap": 70604.4164,
      "rsi14": 51.8957,
      "atr14": 826.3098,
      "avg_volume": 546.9078
    },
    {
      "ts": "2026-03-10T19:00:00Z",
      "open": 70026.99,
      "high": 70301.68,
      "low": 69729.87,
      "close": 70055.27,
      "volume": 812.14362047,
      "ema9": 70547.8825,
      "ema21": 70177.8136,
      "ema50": null,
      "vwap": 70563.7386,
      "rsi14": 52.1391,
      "atr14": 808.1313,
      "avg_volume": 574.4774
    },
    {
      "ts": "2026-03-10T20:00:00Z",
      "open": 70055.28,
      "high": 70362.78,
      "low": 70005.15,
      "close": 70254.98,
      "volume": 633.50834093,
      "ema9": 70489.302,
      "ema21": 70184.8288,
      "ema50": null,
      "vwap": 70545.13,
      "rsi14": 53.9125,
      "atr14": 775.9526,
      "avg_volume": 591.4278
    },
    {
      "ts": "2026-03-10T21:00:00Z",
      "open": 70254.98,
      "high": 70433.35,
      "low": 69550.94,
      "close": 69769.3,
      "volume": 555.62231986,
      "ema9": 70345.3016,
      "ema21": 70147.0534,
      "ema50": null,
      "vwap": 70517.641,
      "rsi14": 49.1435,
      "atr14": 783.5567,
      "avg_volume": 608.6948
    },
    {
      "ts": "2026-03-10T22:00:00Z",
      "open": 69769.3,
      "high": 69883.92,
      "low": 69459.84,
      "close": 69714.43,
      "volume": 304.61675201,
      "ema9": 70219.1273,
      "ema21": 70107.724,
      "ema50": null,
      "vwap": 70498.1304,
      "rsi14": 48.6202,
      "atr14": 757.8798,
      "avg_volume": 599.2147
    },
    {
      "ts": "2026-03-10T23:00:00Z",
      "open": 69714.42,
      "high": 69988.69,
      "low": 69701.01,
      "close": 69960.83,
      "volume": 339.13938612,
      "ema9": 70167.4678,
      "ema21": 70094.37,
      "ema50": null,
      "vwap": 70482.4844,
      "rsi14": 51.1364,
      "atr14": 724.2941,
      "avg_volume": 595.1647
    },
    {
      "ts": "2026-03-11T00:00:00Z",
      "open": 69960.83,
      "high": 70187.74,
      "low": 69766.74,
      "close": 70053.06,
      "volume": 347.96412009,
      "ema9": 70144.5863,
      "ema21": 70090.6146,
      "ema50": null,
      "vwap": 70002.5133,
      "rsi14": 52.0823,
      "atr14": 702.6302,
      "avg_volume": 602.3456
    },
    {
      "ts": "2026-03-11T01:00:00Z",
      "open": 70054.11,
      "high": 70163.01,
      "low": 69891.96,
      "close": 70089.48,
      "volume": 224.14374847,
      "ema9": 70133.565,
      "ema21": 70090.5114,
      "ema50": null,
      "vwap": 70020.3931,
      "rsi14": 52.4736,
      "atr14": 671.8031,
      "avg_volume": 604.8883
    },
    {
      "ts": "2026-03-11T02:00:00Z",
      "open": 70089.48,
      "high": 70137.21,
      "low": 69623.04,
      "close": 69828.11,
      "volume": 216.08729558,
      "ema9": 70072.474,
      "ema21": 70066.6567,
      "ema50": null,
      "vwap": 69977.1846,
      "rsi14": 49.3588,
      "atr14": 660.5436,
      "avg_volume": 606.4178
    },
    {
      "ts": "2026-03-11T03:00:00Z",
      "open": 69820.9,
      "high": 69907.5,
      "low": 69500.0,
      "close": 69556.0,
      "volume": 157.20954936,
      "ema9": 69969.1792,
      "ema21": 70020.2334,
      "ema50": 69325.737,
      "vwap": 69923.526,
      "rsi14": 46.2788,
      "atr14": 642.469,
      "avg_volume": 596.8226
    },
    {
      "ts": "2026-03-11T04:00:00Z",
      "open": 69561.84,
      "high": 70279.02,
      "low": 69500.31,
      "close": 70141.62,
      "volume": 153.64352469,
      "ema9": 70003.6674,
      "ema21": 70031.2685,
      "ema50": 69357.7324,
      "vwap": 69930.5332,
      "rsi14": 53.0665,
      "atr14": 652.2005,
      "avg_volume": 584.0825
    },
    {
      "ts": "2026-03-11T05:00:00Z",
      "open": 70141.4,
      "high": 70212.19,
      "low": 69426.01,
      "close": 69508.02,
      "volume": 210.82911071,
      "ema9": 69904.5379,
      "ema21": 69983.7005,
      "ema50": 69363.626,
      "vwap": 69895.9078,
      "rsi14": 46.2567,
      "atr14": 661.7705,
      "avg_volume": 574.4111
    },
    {
      "ts": "2026-03-11T06:00:00Z",
      "open": 69508.01,
      "high": 70003.79,
      "low": 69491.18,
      "close": 69945.73,
      "volume": 134.64393785,
      "ema9": 69912.7763,
      "ema21": 69980.2486,
      "ema50": 69386.4536,
      "vwap": 69888.2328,
      "rsi14": 50.9404,
      "atr14": 651.1162,
      "avg_volume": 567.2138
    },
    {
      "ts": "2026-03-11T07:00:00Z",
      "open": 69945.74,
      "high": 70033.49,
      "low": 69504.48,
      "close": 69659.45,
      "volume": 150.67922693,
      "ema9": 69862.111,
      "ema21": 69951.0851,
      "ema50": 69397.1594,
      "vwap": 69873.5201,
      "rsi14": 47.9943,
      "atr14": 642.3943,
      "avg_volume": 561.5624
    },
    {
      "ts": "2026-03-11T08:00:00Z",
      "open": 69660.72,
      "high": 69783.66,
      "low": 69505.0,
      "close": 69660.72,
      "volume": 121.21506148,
      "ema9": 69821.8328,
      "ema21": 69924.6883,
      "ema50": 69407.4951,
      "vwap": 69857.7203,
      "rsi14": 48.0087,
      "atr14": 616.4133,
      "avg_volume": 543.2316
    },
    {
      "ts": "2026-03-11T09:00:00Z",
      "open": 69660.72,
      "high": 69757.84,
      "low": 69388.08,
      "close": 69472.01,
      "volume": 137.87264685,
      "ema9": 69751.8683,
      "ema21": 69883.5357,
      "ema50": 69410.0251,
      "vwap": 69834.0454,
      "rsi14": 45.9765,
      "atr14": 598.7952,
      "avg_volume": 508.4229
    },
    {
      "ts": "2026-03-11T10:00:00Z",
      "open": 69472.01,
      "high": 69729.33,
      "low": 69389.99,
      "close": 69616.08,
      "volume": 157.25413235,
      "ema9": 69724.7106,
      "ema21": 69859.2216,
      "ema50": 69418.1057,
      "vwap": 69814.0653,
      "rsi14": 47.7934,
      "atr14": 580.2627,
      "avg_volume": 435.9243
    },
    {
      "ts": "2026-03-11T11:00:00Z",
      "open": 69613.36,
      "high": 69690.3,
      "low": 69155.74,
      "close": 69179.97,
      "volume": 185.01449373,
      "ema9": 69615.7625,
      "ema21": 69797.4714,
      "ema50": 69408.767,
      "vwap": 69774.3038,
      "rsi14": 43.0711,
      "atr14": 576.9982,
      "avg_volume": 389.51
    },
    {
      "ts": "2026-03-11T12:00:00Z",
      "open": 69179.96,
      "high": 69773.79,
      "low": 68980.74,
      "close": 69366.2,
      "volume": 377.76604018,
      "ema9": 69565.85,
      "ema21": 69758.2649,
      "ema50": 69407.0977,
      "vwap": 69715.4996,
      "rsi14": 45.5455,
      "atr14": 592.4305,
      "avg_volume": 350.3163
    },
    {
      "ts": "2026-03-11T13:00:00Z",
      "open": 69366.19,
      "high": 71104.96,
      "low": 69335.02,
      "close": 70192.1,
      "volume": 1080.71239409,
      "ema9": 69691.1,
      "ema21": 69797.7045,
      "ema50": 69437.8821,
      "vwap": 69861.9173,
      "rsi14": 54.9061,
      "atr14": 676.5383,
      "avg_volume": 355.7407
    },
    {
      "ts": "2026-03-11T14:00:00Z",
      "open": 70189.99,
      "high": 71019.25,
      "low": 69963.36,
      "close": 70599.99,
      "volume": 1159.8938513,
      "ema9": 69872.878,
      "ema21": 69870.6395,
      "ema50": 69483.455,
      "vwap": 70022.2611,
      "rsi14": 58.6835,
      "atr14": 703.6348,
      "avg_volume": 372.998
    },
    {
      "ts": "2026-03-11T15:00:00Z",
      "open": 70600.0,
      "high": 70677.5,
      "low": 69724.0,
      "close": 70252.8,
      "volume": 548.79231101,
      "ema9": 69948.8624,
      "ema21": 69905.3814,
      "ema50": 69513.6254,
      "vwap": 70042.2985,
      "rsi14": 54.4987,
      "atr14": 721.4824,
      "avg_volume": 359.8304
    },
    {
      "ts": "2026-03-11T16:00:00Z",
      "open": 70252.8,
      "high": 70850.0,
      "low": 70176.0,
      "close": 70597.96,
      "volume": 570.02542928,
      "ema9": 70078.6819,
      "ema21": 69968.3431,
      "ema50": 69556.1483,
      "vwap": 70090.237,
      "rsi14": 57.7262,
      "atr14": 718.0908,
      "avg_volume": 356.6563
    },
    {
      "ts": "2026-03-11T17:00:00Z",
      "open": 70596.13,
      "high": 71358.48,
      "low": 70521.92,
      "close": 70802.31,
      "volume": 1026.47207957,
      "ema9": 70223.4075,
      "ema21": 70044.1583,
      "ema50": 69605.0174,
      "vwap": 70208.8084,
      "rsi14": 59.5553,
      "atr14": 726.5528,
      "avg_volume": 380.1988
    },
    {
      "ts": "2026-03-11T18:00:00Z",
      "open": 70800.94,
      "high": 70928.45,
      "low": 70435.0,
      "close": 70644.66,
      "volume": 677.19402655,
      "ema9": 70307.658,
      "ema21": 70098.7493,
      "ema50": 69645.7877,
      "vwap": 70249.6455,
      "rsi14": 57.4887,
      "atr14": 709.9026,
      "avg_volume": 398.8276
    },
    {
      "ts": "2026-03-11T19:00:00Z",
      "open": 70644.67,
      "high": 70772.0,
      "low": 70378.01,
      "close": 70670.11,
      "volume": 592.26743409,
      "ema9": 70380.1484,
      "ema21": 70150.6912,
      "ema50": 69685.9572,
      "vwap": 70275.3422,
      "rsi14": 57.7436,
      "atr14": 687.3375,
      "avg_volume": 411.484
    },
    {
      "ts": "2026-03-11T20:00:00Z",
      "open": 70672.95,
      "high": 70733.39,
      "low": 70414.7,
      "close": 70651.31,
      "volume": 575.29770274,
      "ema9": 70434.3807,
      "ema21": 70196.202,
      "ema50": 69723.8142,
      "vwap": 70296.5416,
      "rsi14": 57.4695,
      "atr14": 661.0055,
      "avg_volume": 422.8507
    },
    {
      "ts": "2026-03-11T21:00:00Z",
      "open": 70651.32,
      "high": 70805.18,
      "low": 70505.96,
      "close": 70758.67,
      "volume": 372.77973005,
      "ema9": 70499.2386,
      "ema21": 70247.3355,
      "ema50": 69764.3967,
      "vwap": 70312.5204,
      "rsi14": 58.6761,
      "atr14": 635.1637,
      "avg_volume": 430.2825
    },
    {
      "ts": "2026-03-11T22:00:00Z",
      "open": 70760.01,
      "high": 70843.78,
      "low": 70255.92,
      "close": 70390.94,
      "volume": 397.90637178,
      "ema9": 70477.5789,
      "ema21": 70260.3904,
      "ema50": 69788.9671,
      "vwap": 70320.1812,
      "rsi14": 53.1174,
      "atr14": 631.7848,
      "avg_volume": 439.3735
    },
    {
      "ts": "2026-03-11T23:00:00Z",
      "open": 70390.92,
      "high": 70527.24,
      "low": 70154.84,
      "close": 70208.0,
      "volume": 276.06448621,
      "ema9": 70423.6631,
      "ema21": 70255.6277,
      "ema50": 69805.3997,
      "vwap": 70319.5231,
      "rsi14": 50.5517,
      "atr14": 613.2574,
      "avg_volume": 445.3162
    },
    {
      "ts": "2026-03-12T00:00:00Z",
      "open": 70208.03,
      "high": 70364.97,
      "low": 70144.01,
      "close": 70229.32,
      "volume": 164.3466245,
      "ema9": 70384.7945,
      "ema21": 70253.236,
      "ema50": 69822.0241,
      "vwap": 70246.1,
      "rsi14": 50.8497,
      "atr14": 585.2361,
      "avg_volume": 445.8514
    },
    {
      "ts": "2026-03-12T01:00:00Z",
      "open": 70229.32,
      "high": 70237.29,
      "low": 69763.82,
      "close": 69849.93,
      "volume": 316.05092549,
      "ema9": 70277.8216,
      "ema21": 70216.5719,
      "ema50": 69823.1184,
      "vwap": 70051.5255,
      "rsi14": 45.5856,
      "atr14": 577.2528,
      "avg_volume": 451.1124
    },
    {
      "ts": "2026-03-12T02:00:00Z",
      "open": 69845.99,
      "high": 69899.48,
      "low": 69224.09,
      "close": 69295.67,
      "volume": 319.78136492,
      "ema9": 70081.3913,
      "ema21": 70132.8535,
      "ema50": 69802.4342,
      "vwap": 69820.3571,
      "rsi14": 39.2009,
      "atr14": 584.2626,
      "avg_volume": 460.3693
    },
    {
      "ts": "2026-03-12T03:00:00Z",
      "open": 69295.67,
      "high": 69630.82,
      "low": 69243.06,
      "close": 69449.46,
      "volume": 141.1376064,
      "ema9": 69955.005,
      "ema21": 70070.7268,
      "ema50": 69788.592,
      "vwap": 69763.4946,
      "rsi14": 41.6432,
      "atr14": 570.2267,
      "avg_volume": 459.8922
    },
    {
      "ts": "2026-03-12T04:00:00Z",
      "open": 69449.9,
      "high": 69690.35,
      "low": 69301.89,
      "close": 69375.72,
      "volume": 133.71533355,
      "ema9": 69839.148,
      "ema21": 70007.5444,
      "ema50": 69772.401,
      "vwap": 69725.246,
      "rsi14": 40.797,
      "atr14": 557.2434,
      "avg_volume": 460.5172
    },
    {
      "ts": "2026-03-12T05:00:00Z",
      "open": 69375.71,
      "high": 69556.04,
      "low": 69180.01,
      "close": 69474.34,
      "volume": 124.2591655,
      "ema9": 69766.1864,
      "ema21": 69959.0713,
      "ema50": 69760.7123,
      "vwap": 69691.9059,
      "rsi14": 42.4805,
      "atr14": 544.2996,
      "avg_volume": 459.8366
    },
    {
      "ts": "2026-03-12T06:00:00Z",
      "open": 69474.34,
      "high": 69568.3,
      "low": 69362.17,
      "close": 69501.93,
      "volume": 139.66298204,
      "ema9": 69713.3351,
      "ema21": 69917.513,
      "ema50": 69750.564,
      "vwap": 69669.5383,
      "rsi14": 42.9691,
      "atr14": 520.1446,
      "avg_volume": 458.957
    },
    {
      "ts": "2026-03-12T07:00:00Z",
      "open": 69503.14,
      "high": 69858.06,
      "low": 69415.36,
      "close": 69826.22,
      "volume": 165.30225264,
      "ema9": 69735.9121,
      "ema21": 69909.2136,
      "ema50": 69753.5309,
      "vwap": 69672.8725,
      "rsi14": 48.5059,
      "atr14": 514.6128,
      "avg_volume": 457.9714
    },
    {
      "ts": "2026-03-12T08:00:00Z",
      "open": 69826.21,
      "high": 70120.21,
      "low": 69702.64,
      "close": 69915.45,
      "volume": 173.15521985,
      "ema9": 69771.8197,
      "ema21": 69909.7805,
      "ema50": 69759.8807,
      "vwap": 69697.6362,
      "rsi14": 49.9458,
      "atr14": 507.6812,
      "avg_volume": 447.7409
    },
    {
      "ts": "2026-03-12T09:00:00Z",
      "open": 69915.45,
      "high": 70398.02,
      "low": 69588.26,
      "close": 69958.02,
      "volume": 214.60646405,
      "ema9": 69809.0597,
      "ema21": 69914.166,
      "ema50": 69767.6508,
      "vwap": 69729.8266,
      "rsi14": 50.6548,
      "atr14": 529.2583,
      "avg_volume": 404.4356
    },
    {
      "ts": "2026-03-12T10:00:00Z",
      "open": 69958.02,
      "high": 70527.41,
      "low": 69856.92,
      "close": 70431.09,
      "volume": 265.56826787,
      "ema9": 69933.4658,
      "ema21": 69961.159,
      "ema50": 69793.668,
      "vwap": 69796.5366,
      "rsi14": 57.8067,
      "atr14": 539.3462,
      "avg_volume": 359.7193
    },
    {
      "ts": "2026-03-12T11:00:00Z",
      "open": 70431.09,
      "high": 70819.84,
      "low": 70380.95,
      "close": 70439.47,
      "volume": 369.09682497,
      "ema9": 70034.6666,
      "ema21": 70004.6419,
      "ema50": 69818.9936,
      "vwap": 69906.128,
      "rsi14": 57.9231,
      "atr14": 532.1708,
      "avg_volume": 350.7345
    },
    {
      "ts": "2026-03-12T12:00:00Z",
      "open": 70441.94,
      "high": 70639.12,
      "low": 70293.17,
      "close": 70401.1,
      "volume": 334.37433531,
      "ema9": 70107.9533,
      "ema21": 70040.6835,
      "ema50": 69841.8213,
      "vwap": 69969.0437,
      "rsi14": 57.1461,
      "atr14": 518.8693,
      "avg_volume": 338.952
    },
    {
      "ts": "2026-03-12T13:00:00Z",
      "open": 70401.1,
      "high": 70550.28,
      "low": 69703.9,
      "close": 69994.43,
      "volume": 823.36327972,
      "ema9": 70085.2486,
      "ema21": 70036.4786,
      "ema50": 69847.806,
      "vwap": 69994.4807,
      "rsi14": 49.5585,
      "atr14": 542.2629,
      "avg_volume": 328.7965
    },
    {
      "ts": "2026-03-12T14:00:00Z",
      "open": 69994.46,
      "high": 70694.0,
      "low": 69359.19,
      "close": 69600.89,
      "volume": 1247.09523802,
      "ema9": 69988.3769,
      "ema21": 69996.8797,
      "ema50": 69838.123,
      "vwap": 69966.7173,
      "rsi14": 43.5345,
      "atr14": 598.8734,
      "avg_volume": 357.2916
    },
    {
      "ts": "2026-03-12T15:00:00Z",
      "open": 69600.0,
      "high": 70592.04,
      "low": 69474.1,
      "close": 70353.53,
      "volume": 964.33309513,
      "ema9": 70061.4075,
      "ema21": 70029.3024,
      "ema50": 69858.335,
      "vwap": 69995.0417,
      "rsi14": 54.8403,
      "atr14": 635.9496,
      "avg_volume": 375.8949
    },
    {
      "ts": "2026-03-12T16:00:00Z",
      "open": 70353.52,
      "high": 70591.97,
      "low": 69913.92,
      "close": 70405.94,
      "volume": 859.53509255,
      "ema9": 70130.314,
      "ema21": 70063.5422,
      "ema50": 69879.8097,
      "vwap": 70034.3454,
      "rsi14": 55.5083,
      "atr14": 638.9568,
      "avg_volume": 390.1067
    },
    {
      "ts": "2026-03-12T17:00:00Z",
      "open": 70405.94,
      "high": 70578.17,
      "low": 70081.56,
      "close": 70235.3,
      "volume": 516.9424958,
      "ema9": 70151.3112,
      "ema21": 70079.1566,
      "ema50": 69893.7505,
      "vwap": 70053.1113,
      "rsi14": 52.7712,
      "atr14": 628.7892,
      "avg_volume": 397.3149
    },
    {
      "ts": "2026-03-12T18:00:00Z",
      "open": 70235.31,
      "high": 70325.99,
      "low": 69806.89,
      "close": 69832.88,
      "volume": 381.91777988,
      "ema9": 70087.625,
      "ema21": 70056.7678,
      "ema50": 69891.3635,
      "vwap": 70049.8918,
      "rsi14": 46.8979,
      "atr14": 620.9542,
      "avg_volume": 396.5154
    },
    {
      "ts": "2026-03-12T19:00:00Z",
      "open": 69833.6,
      "high": 70579.99,
      "low": 69778.0,
      "close": 70462.0,
      "volume": 777.44637842,
      "ema9": 70162.5,
      "ema21": 70093.6071,
      "ema50": 69913.7414,
      "vwap": 70070.494,
      "rsi14": 55.2779,
      "atr14": 633.8854,
      "avg_volume": 421.5845
    },
    {
      "ts": "2026-03-12T20:00:00Z",
      "open": 70458.0,
      "high": 70576.11,
      "low": 70113.93,
      "close": 70175.69,
      "volume": 650.15872978,
      "ema9": 70165.138,
      "ema21": 70101.0692,
      "ema50": 69924.0139,
      "vwap": 70086.1062,
      "rsi14": 51.3095,
      "atr14": 621.6207,
      "avg_volume": 445.8751
    },
    {
      "ts": "2026-03-12T21:00:00Z",
      "open": 70175.68,
      "high": 70481.07,
      "low": 70175.68,
      "close": 70279.13,
      "volume": 155.9726576,
      "ema9": 70187.9364,
      "ema21": 70117.2565,
      "ema50": 69937.94,
      "vwap": 70089.9196,
      "rsi14": 52.6325,
      "atr14": 599.0328,
      "avg_volume": 437.8712
    },
    {
      "ts": "2026-03-12T22:00:00Z",
      "open": 70279.12,
      "high": 70316.57,
      "low": 70014.79,
      "close": 70178.55,
      "volume": 170.07469827,
      "ema9": 70186.0591,
      "ema21": 70122.8286,
      "ema50": 69947.3757,
      "vwap": 70091.3667,
      "rsi14": 51.1764,
      "atr14": 577.8004,
      "avg_volume": 430.3859
    },
    {
      "ts": "2026-03-12T23:00:00Z",
      "open": 70178.56,
      "high": 70750.0,
      "low": 70160.31,
      "close": 70531.56,
      "volume": 300.52365452,
      "ema9": 70255.1593,
      "ema21": 70159.986,
      "ema50": 69970.2849,
      "vwap": 70103.4162,
      "rsi14": 55.7987,
      "atr14": 578.6497,
      "avg_volume": 438.3552
    },
    {
      "ts": "2026-03-13T00:00:00Z",
      "open": 70530.02,
      "high": 72023.92,
      "low": 70398.01,
      "close": 71480.68,
      "volume": 927.66932884,
      "ema9": 70500.2634,
      "ema21": 70280.0491,
      "ema50": 70029.516,
      "vwap": 71300.87,
      "rsi14": 65.3084,
      "atr14": 653.454,
      "avg_volume": 478.0529
    },
    {
      "ts": "2026-03-13T01:00:00Z",
      "open": 71479.22,
      "high": 71768.43,
      "low": 71282.97,
      "close": 71672.15,
      "volume": 343.46689281,
      "ema9": 70734.6407,
      "ema21": 70406.6038,
      "ema50": 70093.9331,
      "vwap": 71374.8106,
      "rsi14": 66.8576,
      "atr14": 641.4544,
      "avg_volume": 489.0133
    },
    {
      "ts": "2026-03-13T02:00:00Z",
      "open": 71672.15,
      "high": 71699.05,
      "low": 71053.08,
      "close": 71148.3,
      "volume": 312.03402652,
      "ema9": 70817.3726,
      "ema21": 70474.0307,
      "ema50": 70135.2808,
      "vwap": 71360.0941,
      "rsi14": 59.084,
      "atr14": 641.777,
      "avg_volume": 497.6318
    },
    {
      "ts": "2026-03-13T03:00:00Z",
      "open": 71148.3,
      "high": 71514.63,
      "low": 70962.51,
      "close": 71411.23,
      "volume": 228.58171541,
      "ema9": 70936.1441,
      "ema21": 70559.2306,
      "ema50": 70185.318,
      "vwap": 71352.0232,
      "rsi14": 61.5034,
      "atr14": 635.3729,
      "avg_volume": 500.7958
    },
    {
      "ts": "2026-03-13T04:00:00Z",
      "open": 71410.17,
      "high": 71506.91,
      "low": 71247.33,
      "close": 71392.87,
      "volume": 214.42654336,
      "ema9": 71027.4893,
      "ema21": 70635.016,
      "ema50": 70232.673,
      "vwap": 71355.2347,
      "rsi14": 61.2311,
      "atr14": 608.5305,
      "avg_volume": 502.8594
    },
    {
      "ts": "2026-03-13T05:00:00Z",
      "open": 71392.86,
      "high": 71651.24,
      "low": 71239.87,
      "close": 71557.97,
      "volume": 312.13243235,
      "ema9": 71133.5854,
      "ema21": 70718.9209,
      "ema50": 70284.6454,
      "vwap": 71372.2932,
      "rsi14": 62.8249,
      "atr14": 594.4477,
      "avg_volume": 507.7357
    },
    {
      "ts": "2026-03-13T06:00:00Z",
      "open": 71557.98,
      "high": 71604.85,
      "low": 71186.39,
      "close": 71359.1,
      "volume": 193.4867017,
      "ema9": 71178.6883,
      "ema21": 70777.119,
      "ema50": 70326.7809,
      "vwap": 71373.1456,
      "rsi14": 59.6442,
      "atr14": 581.8771,
      "avg_volume": 504.1316
    },
    {
      "ts": "2026-03-13T07:00:00Z",
      "open": 71359.1,
      "high": 71685.55,
      "low": 71247.35,
      "close": 71632.03,
      "volume": 263.67151597,
      "ema9": 71269.3567,
      "ema21": 70854.8382,
      "ema50": 70377.9671,
      "vwap": 71387.152,
      "rsi14": 62.4537,
      "atr14": 571.6145,
      "avg_volume": 498.8603
    },
    {
      "ts": "2026-03-13T08:00:00Z",
      "open": 71632.02,
      "high": 72170.99,
      "low": 71389.01,
      "close": 71844.78,
      "volume": 432.2556802,
      "ema9": 71384.4413,
      "ema21": 70944.8329,
      "ema50": 70435.4892,
      "vwap": 71442.6538,
      "rsi14": 64.5267,
      "atr14": 586.6406,
      "avg_volume": 503.7544
    },
    {
      "ts": "2026-03-13T09:00:00Z",
      "open": 71844.77,
      "high": 72133.6,
      "low": 71594.68,
      "close": 72017.99,
      "volume": 229.57919165,
      "ema9": 71511.1511,
      "ema21": 71042.3926,
      "ema50": 70497.5481,
      "vwap": 71474.0477,
      "rsi14": 66.1647,
      "atr14": 583.232,
      "avg_volume": 474.0652
    },
    {
      "ts": "2026-03-13T10:00:00Z",
      "open": 72017.99,
      "high": 72609.3,
      "low": 72009.95,
      "close": 72483.94,
      "volume": 542.82432166,
      "ema9": 71705.7089,
      "ema21": 71173.4424,
      "ema50": 70575.4458,
      "vwap": 71595.3219,
      "rsi14": 70.1568,
      "atr14": 584.3832,
      "avg_volume": 438.8516
    },
    {
      "ts": "2026-03-13T11:00:00Z",
      "open": 72483.94,
      "high": 72550.32,
      "low": 72219.99,
      "close": 72246.3,
      "volume": 263.54390067,
      "ema9": 71813.8271,
      "ema21": 71270.9749,
      "ema50": 70640.9695,
      "vwap": 71641.2817,
      "rsi14": 65.8871,
      "atr14": 566.2366,
      "avg_volume": 403.8122
    },
    {
      "ts": "2026-03-13T12:00:00Z",
      "open": 72246.29,
      "high": 72900.01,
      "low": 72223.78,
      "close": 72810.19,
      "volume": 527.39399979,
      "ema9": 72013.0997,
      "ema21": 71410.9036,
      "ema50": 70726.0369,
      "vwap": 71751.7322,
      "rsi14": 70.4783,
      "atr14": 574.0933,
      "avg_volume": 387.2051
    },
    {
      "ts": "2026-03-13T13:00:00Z",
      "open": 72807.65,
      "high": 73633.63,
      "low": 72705.01,
      "close": 73414.64,
      "volume": 1317.03913452,
      "ema9": 72293.4077,
      "ema21": 71593.0614,
      "ema50": 70831.4724,
      "vwap": 72075.0268,
      "rsi14": 74.4482,
      "atr14": 599.4166,
      "avg_volume": 427.21
    },
    {
      "ts": "2026-03-13T14:00:00Z",
      "open": 73414.0,
      "high": 73968.0,
      "low": 72379.31,
      "close": 72423.34,
      "volume": 1444.20635679,
      "ema9": 72319.3942,
      "ema21": 71668.5413,
      "ema50": 70893.8985,
      "vwap": 72237.2874,
      "rsi14": 60.1601,
      "atr14": 670.079,
      "avg_volume": 480.3244
    },
    {
      "ts": "2026-03-13T15:00:00Z",
      "open": 72422.56,
      "high": 72869.07,
      "low": 71743.88,
      "close": 71849.53,
      "volume": 1147.93805601,
      "ema9": 72225.4213,
      "ema21": 71684.9948,
      "ema50": 70931.3743,
      "vwap": 72226.3193,
      "rsi14": 53.7317,
      "atr14": 702.5869,
      "avg_volume": 498.849
    },
    {
      "ts": "2026-03-13T16:00:00Z",
      "open": 71849.53,
      "high": 72125.73,
      "low": 71157.29,
      "close": 71904.49,
      "volume": 805.21377376,
      "ema9": 72161.2351,
      "ema21": 71704.9489,
      "ema50": 70969.5357,
      "vwap": 72184.2055,
      "rsi14": 54.2361,
      "atr14": 721.5764,
      "avg_volume": 506.6017
    },
    {
      "ts": "2026-03-13T17:00:00Z",
      "open": 71901.98,
      "high": 72272.91,
      "low": 70900.03,
      "close": 71043.02,
      "volume": 803.29071661,
      "ema9": 71937.5921,
      "ema21": 71644.7736,
      "ema50": 70972.4174,
      "vwap": 72123.5123,
      "rsi14": 45.8066,
      "atr14": 768.0981,
      "avg_volume": 538.9676
    },
    {
      "ts": "2026-03-13T18:00:00Z",
      "open": 71043.02,
      "high": 71364.79,
      "low": 70836.25,
      "close": 71061.76,
      "volume": 558.07741977,
      "ema9": 71762.4257,
      "ema21": 71591.7723,
      "ema50": 70975.9211,
      "vwap": 72070.3119,
      "rsi14": 46.0032,
      "atr14": 750.9868,
      "avg_volume": 558.3678
    },
    {
      "ts": "2026-03-13T19:00:00Z",
      "open": 71061.76,
      "high": 71325.0,
      "low": 71011.49,
      "close": 71190.64,
      "volume": 447.92759704,
      "ema9": 71648.0685,
      "ema21": 71555.3058,
      "ema50": 70984.3414,
      "vwap": 72034.8965,
      "rsi14": 47.4161,
      "atr14": 719.7385,
      "avg_volume": 565.738
    },
    {
      "ts": "2026-03-13T20:00:00Z",
      "open": 71190.64,
      "high": 71490.12,
      "low": 71151.64,
      "close": 71359.88,
      "volume": 312.67363008,
      "ema9": 71590.4308,
      "ema21": 71537.5398,
      "ema50": 70999.0684,
      "vwap": 72016.0454,
      "rsi14": 49.2924,
      "atr14": 692.5057,
      "avg_volume": 534.9882
    },
    {
      "ts": "2026-03-13T21:00:00Z",
      "open": 71359.88,
      "high": 71500.96,
      "low": 71069.89,
      "close": 71110.76,
      "volume": 171.60474283,
      "ema9": 71494.4967,
      "ema21": 71498.7416,
      "ema50": 71003.4485,
      "vwap": 72004.5725,
      "rsi14": 46.6535,
      "atr14": 673.8317,
      "avg_volume": 526.3951
    },
    {
      "ts": "2026-03-13T22:00:00Z",
      "open": 71110.77,
      "high": 71210.86,
      "low": 70555.59,
      "close": 70825.07,
      "volume": 328.86659166,
      "ema9": 71360.6113,
      "ema21": 71437.4987,
      "ema50": 70996.4532,
      "vwap": 71973.6398,
      "rsi14": 43.7601,
      "atr14": 672.5059,
      "avg_volume": 527.2367
    },
    {
      "ts": "2026-03-13T23:00:00Z",
      "open": 70827.51,
      "high": 71026.24,
      "low": 70710.73,
      "close": 70944.33,
      "volume": 176.31206821,
      "ema9": 71277.3551,
      "ema21": 71392.6652,
      "ema50": 70994.4092,
      "vwap": 71958.1659,
      "rsi14": 45.2856,
      "atr14": 647.0062,
      "avg_volume": 524.6232
    },
    {
      "ts": "2026-03-14T00:00:00Z",
      "open": 70944.32,
      "high": 70961.84,
      "low": 70567.65,
      "close": 70640.67,
      "volume": 204.6340469,
      "ema9": 71150.018,
      "ema21": 71324.302,
      "ema50": 70980.5371,
      "vwap": 70723.3867,
      "rsi14": 42.1506,
      "atr14": 628.9479,
      "avg_volume": 524.1336
    },
    {
      "ts": "2026-03-14T01:00:00Z",
      "open": 70640.64,
      "high": 70919.57,
      "low": 70490.02,
      "close": 70839.2,
      "volume": 209.76813793,
      "ema9": 71087.8544,
      "ema21": 71280.2018,
      "ema50": 70974.9944,
      "vwap": 70736.654,
      "rsi14": 44.8392,
      "atr14": 614.7052,
      "avg_volume": 519.0154
    },
    {
      "ts": "2026-03-14T02:00:00Z",
      "open": 70836.29,
      "high": 70914.11,
      "low": 70745.94,
      "close": 70796.94,
      "volume": 124.23338763,
      "ema9": 71029.6715,
      "ema21": 71236.2689,
      "ema50": 70968.0119,
      "vwap": 70755.6459,
      "rsi14": 44.3665,
      "atr14": 582.8098,
      "avg_volume": 515.5527
    },
    {
      "ts": "2026-03-14T03:00:00Z",
      "open": 70798.64,
      "high": 71182.72,
      "low": 70798.64,
      "close": 71087.41,
      "volume": 136.45005039,
      "ema9": 71041.2192,
      "ema21": 71222.7363,
      "ema50": 70972.6942,
      "vwap": 70809.6687,
      "rsi14": 48.3935,
      "atr14": 568.7363,
      "avg_volume": 509.1916
    },
    {
      "ts": "2026-03-14T04:00:00Z",
      "open": 71087.41,
      "high": 71316.0,
      "low": 71027.04,
      "close": 71040.24,
      "volume": 189.75894682,
      "ema9": 71041.0234,
      "ema21": 71206.1457,
      "ema50": 70975.343,
      "vwap": 70879.4624,
      "rsi14": 47.7886,
      "atr14": 548.7522,
      "avg_volume": 497.0668
    },
    {
      "ts": "2026-03-14T05:00:00Z",
      "open": 71040.24,
      "high": 71163.31,
      "low": 70923.88,
      "close": 71028.99,
      "volume": 126.35880364,
      "ema9": 71038.6167,
      "ema21": 71190.0407,
      "ema50": 70977.4468,
      "vwap": 70899.7654,
      "rsi14": 47.6356,
      "atr14": 526.6578,
      "avg_volume": 491.9058
    },
    {
      "ts": "2026-03-14T06:00:00Z",
      "open": 71028.99,
      "high": 71028.99,
      "low": 70236.02,
      "close": 70638.29,
      "volume": 325.95794402,
      "ema9": 70958.5514,
      "ema21": 71139.8815,
      "ema50": 70964.1466,
      "vwap": 70834.1037,
      "rsi14": 42.5433,
      "atr14": 545.6801,
      "avg_volume": 481.0625
    },
    {
      "ts": "2026-03-14T07:00:00Z",
      "open": 70640.64,
      "high": 70762.4,
      "low": 70491.15,
      "close": 70617.28,
      "volume": 126.07993986,
      "ema9": 70890.2971,
      "ema21": 71092.3723,
      "ema50": 70950.544,
      "vwap": 70815.7152,
      "rsi14": 42.2816,
      "atr14": 526.0779,
      "avg_volume": 474.1893
    },
    {
      "ts": "2026-03-14T08:00:00Z",
      "open": 70617.27,
      "high": 70728.19,
      "low": 70550.12,
      "close": 70599.63,
      "volume": 93.09027322,
      "ema9": 70832.1637,
      "ema21": 71047.5775,
      "ema50": 70936.7826,
      "vwap": 70804.2186,
      "rsi14": 42.0475,
      "atr14": 501.2202,
      "avg_volume": 452.4741
    },
    {
      "ts": "2026-03-14T09:00:00Z",
      "open": 70599.64,
      "high": 70741.4,
      "low": 70404.14,
      "close": 70523.99,
      "volume": 129.33087741,
      "ema9": 70770.5289,
      "ema21": 70999.9787,
      "ema50": 70920.5947,
      "vwap": 70784.9852,
      "rsi14": 41.0,
      "atr14": 489.5088,
      "avg_volume": 393.0887
    },
    {
      "ts": "2026-03-14T10:00:00Z",
      "open": 70520.92,
      "high": 70592.45,
      "low": 70372.99,
      "close": 70580.02,
      "volume": 88.75219288,
      "ema9": 70732.4272,
      "ema21": 70961.8006,
      "ema50": 70907.2388,
      "vwap": 70771.335,
      "rsi14": 42.1497,
      "atr14": 470.2196,
      "avg_volume": 325.316
    },
    {
      "ts": "2026-03-14T11:00:00Z",
      "open": 70580.01,
      "high": 70789.62,
      "low": 70570.56,
      "close": 70754.52,
      "volume": 88.30433203,
      "ema9": 70736.8457,
      "ema21": 70942.9569,
      "ema50": 70901.2498,
      "vwap": 70768.1514,
      "rsi14": 45.6984,
      "atr14": 452.2796,
      "avg_volume": 272.3343
    },
    {
      "ts": "2026-03-14T12:00:00Z",
      "open": 70754.51,
      "high": 70852.15,
      "low": 70623.12,
      "close": 70784.01,
      "volume": 125.97192135,
      "ema9": 70746.2786,
      "ema21": 70928.5072,
      "ema50": 70896.6522,
      "vwap": 70767.1879,
      "rsi14": 46.298,
      "atr14": 436.3332,
      "avg_volume": 238.3722
    },
    {
      "ts": "2026-03-14T13:00:00Z",
      "open": 70784.0,
      "high": 70940.58,
      "low": 70709.43,
      "close": 70865.49,
      "volume": 115.13124887,
      "ema9": 70770.1209,
      "ema21": 70922.7784,
      "ema50": 70895.4302,
      "vwap": 70771.1279,
      "rsi14": 48.0061,
      "atr14": 421.6773,
      "avg_volume": 203.9642
    },
    {
      "ts": "2026-03-14T14:00:00Z",
      "open": 70869.42,
      "high": 70969.99,
      "low": 70581.96,
      "close": 70616.48,
      "volume": 137.27335341,
      "ema9": 70739.3927,
      "ema21": 70894.9331,
      "ema50": 70884.4909,
      "vwap": 70768.1416,
      "rsi14": 43.4568,
      "atr14": 419.2739,
      "avg_volume": 182.924
    },
    {
      "ts": "2026-03-14T15:00:00Z",
      "open": 70616.47,
      "high": 70739.92,
      "low": 70503.41,
      "close": 70597.33,
      "volume": 114.8866925,
      "ema9": 70710.9802,
      "ema21": 70867.8782,
      "ema50": 70873.2297,
      "vwap": 70760.5387,
      "rsi14": 43.1184,
      "atr14": 406.2193,
      "avg_volume": 166.272
    },
    {
      "ts": "2026-03-14T16:00:00Z",
      "open": 70597.32,
      "high": 70725.32,
      "low": 70509.25,
      "close": 70694.21,
      "volume": 102.91856412,
      "ema9": 70707.6261,
      "ema21": 70852.0902,
      "ema50": 70866.2093,
      "vwap": 70755.5757,
      "rsi14": 45.4335,
      "atr14": 392.6372,
      "avg_volume": 155.7842
    },
    {
      "ts": "2026-03-14T17:00:00Z",
      "open": 70690.3,
      "high": 70750.0,
      "low": 70597.89,
      "close": 70633.0,
      "volume": 78.68010042,
      "ema9": 70692.7009,
      "ema21": 70832.1729,
      "ema50": 70857.0639,
      "vwap": 70752.598,
      "rsi14": 44.2092,
      "atr14": 375.4567,
      "avg_volume": 151.138
    },
    {
      "ts": "2026-03-14T18:00:00Z",
      "open": 70633.0,
      "high": 70720.0,
      "low": 70560.01,
      "close": 70672.77,
      "volume": 72.81633325,
      "ema9": 70688.7147,
      "ema21": 70817.6817,
      "ema50": 70849.8367,
      "vwap": 70749.74,
      "rsi14": 45.2417,
      "atr14": 360.0662,
      "avg_volume": 138.3355
    },
    {
      "ts": "2026-03-14T19:00:00Z",
      "open": 70672.77,
      "high": 70751.6,
      "low": 70606.26,
      "close": 70717.99,
      "volume": 81.02092585,
      "ema9": 70694.5698,
      "ema21": 70808.6189,
      "ema50": 70844.6662,
      "vwap": 70747.9873,
      "rsi14": 46.455,
      "atr14": 344.7287,
      "avg_volume": 133.5709
    },
    {
      "ts": "2026-03-14T20:00:00Z",
      "open": 70717.98,
      "high": 70874.98,
      "low": 70661.09,
      "close": 70821.57,
      "volume": 124.28693468,
      "ema9": 70719.9698,
      "ema21": 70809.7962,
      "ema50": 70843.7605,
      "vwap": 70749.6719,
      "rsi14": 49.2301,
      "atr14": 335.383,
      "avg_volume": 129.5535
    },
    {
      "ts": "2026-03-14T21:00:00Z",
      "open": 70821.57,
      "high": 70839.79,
      "low": 70674.36,
      "close": 70822.33,
      "volume": 84.84299874,
      "ema9": 70740.4419,
      "ema21": 70810.9357,
      "ema50": 70842.9201,
      "vwap": 70750.5306,
      "rsi14": 49.2509,
      "atr14": 323.2435,
      "avg_volume": 123.3073
    },
    {
      "ts": "2026-03-14T22:00:00Z",
      "open": 70822.33,
      "high": 70822.94,
      "low": 70712.13,
      "close": 70731.15,
      "volume": 79.29896373,
      "ema9": 70738.5835,
      "ema21": 70803.6824,
      "ema50": 70838.5369,
      "vwap": 70750.6612,
      "rsi14": 46.7769,
      "atr14": 308.0697,
      "avg_volume": 121.0606
    },
    {
      "ts": "2026-03-14T23:00:00Z",
      "open": 70731.14,
      "high": 71263.99,
      "low": 70731.14,
      "close": 71232.02,
      "volume": 214.23642357,
      "ema9": 70837.2708,
      "ema21": 70842.6222,
      "ema50": 70853.9676,
      "vwap": 70772.601,
      "rsi14": 58.9697,
      "atr14": 324.1254,
      "avg_volume": 124.9499
    },
    {
      "ts": "2026-03-15T00:00:00Z",
      "open": 71232.01,
      "high": 71232.01,
      "low": 70971.06,
      "close": 71002.73,
      "volume": 246.13721839,
      "ema9": 70870.3626,
      "ema21": 70857.1775,
      "ema50": 70859.8014,
      "vwap": 71068.6,
      "rsi14": 52.9855,
      "atr14": 319.6136,
      "avg_volume": 127.7688
    },
    {
      "ts": "2026-03-15T01:00:00Z",
      "open": 71002.72,
      "high": 71052.37,
      "low": 70868.41,
      "close": 71001.14,
      "volume": 232.14792797,
      "ema9": 70896.5181,
      "ema21": 70870.265,
      "ema50": 70865.3441,
      "vwap": 71022.6705,
      "rsi14": 52.9454,
      "atr14": 309.9241,
      "avg_volume": 133.0583
    },
    {
      "ts": "2026-03-15T02:00:00Z",
      "open": 71001.14,
      "high": 71633.44,
      "low": 71001.14,
      "close": 71458.53,
      "volume": 260.21004172,
      "ema9": 71008.9205,
      "ema21": 70923.7436,
      "ema50": 70888.6063,
      "vwap": 71143.0689,
      "rsi14": 61.8866,
      "atr14": 332.9509,
      "avg_volume": 129.7709
    },
    {
      "ts": "2026-03-15T03:00:00Z",
      "open": 71458.03,
      "high": 71537.07,
      "low": 71242.18,
      "close": 71364.6,
      "volume": 182.56955645,
      "ema9": 71080.0564,
      "ema21": 70963.8215,
      "ema50": 70907.2727,
      "vwap": 71190.2868,
      "rsi14": 59.3907,
      "atr14": 330.2323,
      "avg_volume": 132.5953
    },
    {
      "ts": "2026-03-15T04:00:00Z",
      "open": 71364.6,
      "high": 71675.59,
      "low": 71334.74,
      "close": 71596.02,
      "volume": 174.43685909,
      "ema9": 71183.2491,
      "ema21": 71021.2941,
      "ema50": 70934.2824,
      "vwap": 71245.2472,
      "rsi14": 63.3161,
      "atr14": 330.9907,
      "avg_volume": 136.6627
    },
    {
      "ts": "2026-03-15T05:00:00Z",
      "open": 71598.4,
      "high": 71802.0,
      "low": 71481.6,
      "close": 71500.16,
      "volume": 149.02480512,
      "ema9": 71246.6313,
      "ema21": 71064.8273,
      "ema50": 70956.4737,
      "vwap": 71287.0785,
      "rsi14": 60.6988,
      "atr14": 330.2342,
      "avg_volume": 137.6474
    },
    {
      "ts": "2026-03-15T06:00:00Z",
      "open": 71500.17,
      "high": 71608.17,
      "low": 71394.53,
      "close": 71462.0,
      "volume": 113.77937317,
      "ema9": 71289.705,
      "ema21": 71100.9339,
      "ema50": 70976.2983,
      "vwap": 71303.9284,
      "rsi14": 59.6419,
      "atr14": 321.9061,
      "avg_volume": 138.8987
    },
    {
      "ts": "2026-03-15T07:00:00Z",
      "open": 71461.99,
      "high": 71685.18,
      "low": 71413.49,
      "close": 71464.07,
      "volume": 101.08120827,
      "ema9": 71324.578,
      "ema21": 71133.9463,
      "ema50": 70995.4266,
      "vwap": 71318.9574,
      "rsi14": 59.6829,
      "atr14": 318.3192,
      "avg_volume": 139.5376
    },
    {
      "ts": "2026-03-15T08:00:00Z",
      "open": 71464.07,
      "high": 71734.05,
      "low": 71464.07,
      "close": 71723.85,
      "volume": 130.36069199,
      "ema9": 71404.4324,
      "ema21": 71187.5739,
      "ema50": 71023.9922,
      "vwap": 71345.337,
      "rsi14": 64.5513,
      "atr14": 314.8664,
      "avg_volume": 139.757
    },
    {
      "ts": "2026-03-15T09:00:00Z",
      "open": 71723.85,
      "high": 71957.56,
      "low": 71715.2,
      "close": 71798.88,
      "volume": 162.41131139,
      "ema9": 71483.3219,
      "ema21": 71243.1472,
      "ema50": 71054.38,
      "vwap": 71389.6942,
      "rsi14": 65.8345,
      "atr14": 309.6874,
      "avg_volume": 142.121
    },
    {
      "ts": "2026-03-15T10:00:00Z",
      "open": 71798.87,
      "high": 71925.98,
      "low": 71726.59,
      "close": 71794.0,
      "volume": 63.24055433,
      "ema9": 71545.4575,
      "ema21": 71293.2247,
      "ema50": 71083.3847,
      "vwap": 71404.5282,
      "rsi14": 65.668,
      "atr14": 301.809,
      "avg_volume": 138.4194
    },
    {
      "ts": "2026-03-15T11:00:00Z",
      "open": 71794.0,
      "high": 71900.0,
      "low": 71674.32,
      "close": 71856.99,
      "volume": 104.28062826,
      "ema9": 71607.764,
      "ema21": 71344.4761,
      "ema50": 71113.7221,
      "vwap": 71426.5779,
      "rsi14": 66.834,
      "atr14": 296.3712,
      "avg_volume": 137.8891
    },
    {
      "ts": "2026-03-15T12:00:00Z",
      "open": 71856.98,
      "high": 71856.99,
      "low": 71580.89,
      "close": 71624.85,
      "volume": 95.28635685,
      "ema9": 71611.1812,
      "ema21": 71369.9646,
      "ema50": 71133.7664,
      "vwap": 71438.9203,
      "rsi14": 58.8954,
      "atr14": 294.9233,
      "avg_volume": 137.5075
    },
    {
      "ts": "2026-03-15T13:00:00Z",
      "open": 71624.85,
      "high": 71697.68,
      "low": 71274.01,
      "close": 71610.09,
      "volume": 277.09167506,
      "ema9": 71610.963,
      "ema21": 71391.7942,
      "ema50": 71152.4457,
      "vwap": 71449.5999,
      "rsi14": 58.4202,
      "atr14": 304.1195,
      "avg_volume": 147.428
    },
    {
      "ts": "2026-03-15T14:00:00Z",
      "open": 71610.08,
      "high": 71636.36,
      "low": 71351.84,
      "close": 71633.43,
      "volume": 176.62446752,
      "ema9": 71615.4564,
      "ema21": 71413.7611,
      "ema50": 71171.3079,
      "vwap": 71456.1065,
      "rsi14": 58.9838,
      "atr14": 302.7195,
      "avg_volume": 152.6184
    },
    {
      "ts": "2026-03-15T15:00:00Z",
      "open": 71633.42,
      "high": 71633.42,
      "low": 71420.28,
      "close": 71484.91,
      "volume": 123.59624309,
      "ema9": 71589.3471,
      "ema21": 71420.2292,
      "ema50": 71183.606,
      "vwap": 71458.8129,
      "rsi14": 53.9712,
      "atr14": 296.3217,
      "avg_volume": 154.7472
    },
    {
      "ts": "2026-03-15T16:00:00Z",
      "open": 71484.92,
      "high": 71603.09,
      "low": 71334.31,
      "close": 71448.09,
      "volume": 200.15623986,
      "ema9": 71561.0957,
      "ema21": 71422.762,
      "ema50": 71193.9779,
      "vwap": 71459.0292,
      "rsi14": 52.7739,
      "atr14": 294.3544,
      "avg_volume": 158.5407
    },
    {
      "ts": "2026-03-15T17:00:00Z",
      "open": 71448.09,
      "high": 71999.5,
      "low": 71420.29,
      "close": 71832.0,
      "volume": 165.24000422,
      "ema9": 71615.2766,
      "ema21": 71459.9654,
      "ema50": 71218.9984,
      "vwap": 71475.3186,
      "rsi14": 62.1922,
      "atr14": 314.7012,
      "avg_volume": 162.5605
    },
    {
      "ts": "2026-03-15T18:00:00Z",
      "open": 71832.01,
      "high": 71900.0,
      "low": 71328.01,
      "close": 71398.78,
      "volume": 213.79504148,
      "ema9": 71571.9772,
      "ema21": 71454.4031,
      "ema50": 71226.0486,
      "vwap": 71479.8314,
      "rsi14": 50.0599,
      "atr14": 333.079,
      "avg_volume": 169.2853
    },
    {
      "ts": "2026-03-15T19:00:00Z",
      "open": 71398.79,
      "high": 71586.71,
      "low": 71346.0,
      "close": 71565.09,
      "volume": 122.86421518,
      "ema9": 71570.5998,
      "ema21": 71464.4656,
      "ema50": 71239.3444,
      "vwap": 71480.5563,
      "rsi14": 53.7869,
      "atr14": 326.4812,
      "avg_volume": 164.7167
    },
    {
      "ts": "2026-03-15T20:00:00Z",
      "open": 71565.09,
      "high": 71935.99,
      "low": 71437.53,
      "close": 71739.41,
      "volume": 165.47922497,
      "ema9": 71604.3618,
      "ema21": 71489.4605,
      "ema50": 71258.9548,
      "vwap": 71491.2582,
      "rsi14": 57.3776,
      "atr14": 338.7654,
      "avg_volume": 160.6838
    },
    {
      "ts": "2026-03-15T21:00:00Z",
      "open": 71739.41,
      "high": 72299.13,
      "low": 71636.75,
      "close": 72112.32,
      "volume": 293.78126793,
      "ema9": 71705.9535,
      "ema21": 71546.0841,
      "ema50": 71292.4201,
      "vwap": 71532.3332,
      "rsi14": 63.8486,
      "atr14": 361.8807,
      "avg_volume": 163.7655
    },
    {
      "ts": "2026-03-15T22:00:00Z",
      "open": 72115.24,
      "high": 73090.68,
      "low": 71729.81,
      "close": 72763.99,
      "volume": 1203.32586319,
      "ema9": 71917.5608,
      "ema21": 71656.8028,
      "ema50": 71350.1287,
      "vwap": 71774.0768,
      "rsi14": 71.8824,
      "atr14": 433.2371,
      "avg_volume": 210.9213
    },
    {
      "ts": "2026-03-15T23:00:00Z",
      "open": 72766.4,
      "high": 73220.8,
      "low": 72414.0,
      "close": 72830.01,
      "volume": 828.69867099,
      "ema9": 72100.0506,
      "ema21": 71763.458,
      "ema50": 71408.1633,
      "vwap": 71924.1185,
      "rsi14": 72.548,
      "atr14": 459.9202,
      "avg_volume": 243.2277
    },
    {
      "ts": "2026-03-16T00:00:00Z",
      "open": 72830.01,
      "high": 73032.41,
      "low": 72444.55,
      "close": 72547.4,
      "volume": 410.01868931,
      "ema9": 72189.5205,
      "ema21": 71834.7255,
      "ema50": 71452.8392,
      "vwap": 72674.7867,
      "rsi14": 65.4101,
      "atr14": 469.0587,
      "avg_volume": 255.0068
    },
    {
      "ts": "2026-03-16T01:00:00Z",
      "open": 72547.4,
      "high": 72642.24,
      "low": 72373.2,
      "close": 72424.52,
      "volume": 74.25442023,
      "ema9": 72236.5204,
      "ema21": 71888.3432,
      "ema50": 71490.9444,
      "vwap": 72644.9177,
      "rsi14": 62.5294,
      "atr14": 454.7717,
      "avg_volume": 251.2683
    }
  ]
}